{"Type":"maqra","Number":201,"DefaultUrl":"https://quanticapps.com/quran-high/AhmeD_ALLHDaN/046.mp3","TotalDurationMs":null,"Segments":[{"I":0,"S":46,"V":1,"Url":"https://quanticapps.com/quran-high/AhmeD_ALLHDaN/046.mp3","StartMs":4269,"EndMs":9829,"DurationMs":5560},{"I":1,"S":46,"V":2,"Url":"https://quanticapps.com/quran-high/AhmeD_ALLHDaN/046.mp3","StartMs":9829,"EndMs":16509,"DurationMs":6680},{"I":2,"S":46,"V":3,"Url":"https://quanticapps.com/quran-high/AhmeD_ALLHDaN/046.mp3","StartMs":16509,"EndMs":37499,"DurationMs":20990},{"I":3,"S":46,"V":4,"Url":"https://quanticapps.com/quran-high/AhmeD_ALLHDaN/046.mp3","StartMs":37499,"EndMs":71599,"DurationMs":34100},{"I":4,"S":46,"V":5,"Url":"https://quanticapps.com/quran-high/AhmeD_ALLHDaN/046.mp3","StartMs":71599,"EndMs":93495,"DurationMs":21896},{"I":5,"S":46,"V":6,"Url":"https://quanticapps.com/quran-high/AhmeD_ALLHDaN/046.mp3","StartMs":93495,"EndMs":105701,"DurationMs":12206},{"I":6,"S":46,"V":7,"Url":"https://quanticapps.com/quran-high/AhmeD_ALLHDaN/046.mp3","StartMs":105701,"EndMs":122428,"DurationMs":16727},{"I":7,"S":46,"V":8,"Url":"https://quanticapps.com/quran-high/AhmeD_ALLHDaN/046.mp3","StartMs":122428,"EndMs":148034,"DurationMs":25606},{"I":8,"S":46,"V":9,"Url":"https://quanticapps.com/quran-high/AhmeD_ALLHDaN/046.mp3","StartMs":148034,"EndMs":170918,"DurationMs":22884},{"I":9,"S":46,"V":10,"Url":"https://quanticapps.com/quran-high/AhmeD_ALLHDaN/046.mp3","StartMs":170918,"EndMs":198242,"DurationMs":27324},{"I":10,"S":46,"V":11,"Url":"https://quanticapps.com/quran-high/AhmeD_ALLHDaN/046.mp3","StartMs":198242,"EndMs":220012,"DurationMs":21770},{"I":11,"S":46,"V":12,"Url":"https://quanticapps.com/quran-high/AhmeD_ALLHDaN/046.mp3","StartMs":220012,"EndMs":240387,"DurationMs":20375},{"I":12,"S":46,"V":13,"Url":"https://quanticapps.com/quran-high/AhmeD_ALLHDaN/046.mp3","StartMs":240387,"EndMs":253036,"DurationMs":12649},{"I":13,"S":46,"V":14,"Url":"https://quanticapps.com/quran-high/AhmeD_ALLHDaN/046.mp3","StartMs":253036,"EndMs":267014,"DurationMs":13978},{"I":14,"S":46,"V":15,"Url":"https://quanticapps.com/quran-high/AhmeD_ALLHDaN/046.mp3","StartMs":267014,"EndMs":327455,"DurationMs":60441},{"I":15,"S":46,"V":16,"Url":"https://quanticapps.com/quran-high/AhmeD_ALLHDaN/046.mp3","StartMs":327455,"EndMs":353070,"DurationMs":25615},{"I":16,"S":46,"V":17,"Url":"https://quanticapps.com/quran-high/AhmeD_ALLHDaN/046.mp3","StartMs":353070,"EndMs":394606,"DurationMs":41536},{"I":17,"S":46,"V":18,"Url":"https://quanticapps.com/quran-high/AhmeD_ALLHDaN/046.mp3","StartMs":394606,"EndMs":416625,"DurationMs":22019},{"I":18,"S":46,"V":19,"Url":"https://quanticapps.com/quran-high/AhmeD_ALLHDaN/046.mp3","StartMs":416625,"EndMs":429949,"DurationMs":13324},{"I":19,"S":46,"V":20,"Url":"https://quanticapps.com/quran-high/AhmeD_ALLHDaN/046.mp3","StartMs":429949,"EndMs":460483,"DurationMs":30534}]}