{"Id":316,"LanguageCodes":["sk","slk"],"Name":"slk-hadiabdollahian","Author":"Hadi Abdollahian","Language":"Slovak","Description":"Slovak","Direction":"ltr","Source":"https://www.alqurantranslation.com/ , Contact:+989354664487","Translations":[{"SurahNumber":72,"VerseNumber":20,"Text":"Say ja kult len moj Lord ja never set any idols Him"},{"SurahNumber":72,"VerseNumber":21,"Text":"Say ja nie possess power harm ona nor guide ona"},{"SurahNumber":72,"VerseNumber":22,"Text":"Say Ziaden 1 chranit mna GOD nor mozem ja zalozit any inaksie refuge Him"},{"SurahNumber":72,"VerseNumber":23,"Text":"Ja deliver GOD's proclamations odkaz Those disobey GOD Jeho posol incur zapalit Hell wherein they abide forever"},{"SurahNumber":72,"VerseNumber":24,"Text":"Once they see co awaiting them they robit zalozit out kto je skutocne chaby v power fewer v zvazok"},{"SurahNumber":72,"VerseNumber":25,"Text":"Say ja nie zauzlit co promised ona happen skoro al moj Lord zdrzat it for awhile"},{"SurahNumber":72,"VerseNumber":26,"Text":"He bol Knower buduci; He nie reveal buduci ktokolvek"},{"SurahNumber":72,"VerseNumber":27,"Text":"Len do posol He zvolit si robit He reveal minuly buduci specific zvest"},{"SurahNumber":72,"VerseNumber":28,"Text":"This bol zistit lenze they delivered ich Lord's odkaz. He je fully aware z co they have He pocitat zvazok all things"}]}