{"Id":82,"LanguageCodes":["cs","ces"],"Name":"ces-prekladihrbek","Author":"Preklad I. Hrbek","Language":"Czech","Description":"Czech","Direction":"ltr","Source":"http://tanzil.net","Translations":[{"SurahNumber":18,"VerseNumber":83,"Text":"A vyptávají se tě na Dvourohého. Odpověz: \"Budu vám vyprávět příběh o něm"},{"SurahNumber":18,"VerseNumber":84,"Text":"Upevnili jsme moc jeho na zemi a zahrnuli jsme jej prostředky k věcem všem"},{"SurahNumber":18,"VerseNumber":85,"Text":"A on za nebeským šel lanem"},{"SurahNumber":18,"VerseNumber":86,"Text":"a když dospěl k slunce západu, shledal, že zapadá v prameni vroucím, a nalezl lid nějaký poblíže. I řekli jsme mu: \"Dvourohý, na tobě je, zda potrestáš je, či zda zachováš se k nim dobře"},{"SurahNumber":18,"VerseNumber":87,"Text":"Odpověděl: \"Toho, kdo z nich je nespravedlivý, potrestám a potom bude navrácen k Pánu svému, jenž potrestá jej trestem odporným"},{"SurahNumber":18,"VerseNumber":88,"Text":"A co týká se toho, kdo věří a zbožné skutky konal, tomu dostane se odměny překrásné a rozkaz, jejž dáme mu, bude snadný"},{"SurahNumber":18,"VerseNumber":89,"Text":"Potom sledoval lano jiné"},{"SurahNumber":18,"VerseNumber":90,"Text":"a když dospěl k slunce východu, shledal, že vychází nad lidem, jemuž jsme nedali na ochranu proti němu clony žádné"},{"SurahNumber":18,"VerseNumber":91,"Text":"A tak tomu bylo a My jsme již obsáhli ve vědění Svém vše, co u něho bylo"},{"SurahNumber":18,"VerseNumber":92,"Text":"Po té sledoval další lano"},{"SurahNumber":18,"VerseNumber":93,"Text":"až k místu mezi dvěma hrázemi dospěl a pod nimi lid, jenž sotva chápal řeč mluvenou, našel"},{"SurahNumber":18,"VerseNumber":94,"Text":"I řekli mu: \"Dvourohý, věru Gog a Magog šíří spoušť po zemi; máme ti poplatek zaplatit, abys mezi námi a jimi hráz vystavěl"},{"SurahNumber":18,"VerseNumber":95,"Text":"Odpověděl: \"To, co mi propůjčil Pán můj, je lepší než poplatek. Pomozte mi horlivostí svou a zřídím mezi vámi a jimi hráz mocnou"},{"SurahNumber":18,"VerseNumber":96,"Text":"Přineste mi kusy železa!\" A když je narovnal mezi dvě úbočí, rozkázal: \"Foukejte!\" Když z toho vznikl oheň, dodal: \"Přineste mi k vylití do něho mosaz roztavenou"},{"SurahNumber":18,"VerseNumber":97,"Text":"A nebyli Gog a Magog schopni ji přelézt ani otvor udělat v ní"},{"SurahNumber":18,"VerseNumber":98,"Text":"I řekl Dvourohý: \"Toto je od Pána mého milosrdenství, a až splní se slib Pána mého, na prach ji rozdrtí, vždyť Pána mého slib je vždy pravdivý"},{"SurahNumber":18,"VerseNumber":99,"Text":"V ten den je ponecháme, aby jeden na druhého ve vlnách dorážel. A bude zatroubeno na pozoun a shromáždíme je všechny najednou"},{"SurahNumber":18,"VerseNumber":100,"Text":"V ten den pak představíme peklo nevěřícím rovnou"},{"SurahNumber":18,"VerseNumber":101,"Text":"těm, jejichž oči se zavíraly před připomenutím Mým, a těm, kteří nebyli schopni slyšení"}]}