{"Id":197,"LanguageCodes":["hu","hun"],"Name":"hun-drahmedabdelrah-la","Author":"Dr. Ahmed Abdel Rahman Okfat Tashaab","Language":"Hungarian","Description":"Hungarian - Transliteration","Direction":"ltr","Source":"https://archive.org/ , King Fahd Quran Complex","Translations":[{"SurahNumber":87,"VerseNumber":1,"Text":"Magasztald a te Legmagasztosabb Urad Nevet! Hizb"},{"SurahNumber":87,"VerseNumber":2,"Text":"Aki (mindent) megteremtett es megformazott"},{"SurahNumber":87,"VerseNumber":3,"Text":"— Aki mindennek elore megszabta a merteket, es az igazak utjara vezetett"},{"SurahNumber":87,"VerseNumber":4,"Text":"Es, Aki a legeloket keltette eletre"},{"SurahNumber":87,"VerseNumber":5,"Text":"Majd azt sotetbarna lehullott levelekke (azokhoz hasonlova) tette"},{"SurahNumber":87,"VerseNumber":6,"Text":"Elrecitaltatjuk veled ( Muhammad- Allah aldja meg es adjon Neki orok udvosseget- a Korant) ugy, hogy nem felejted el"},{"SurahNumber":87,"VerseNumber":7,"Text":"Kiveve azt, amit Allah is akar. Mert O tudja azt is, ami elhangzott es azt, ami rejtve marad"},{"SurahNumber":87,"VerseNumber":8,"Text":"Megkonnyitjuk neked (Muhammad- Allah aldja meg es adjon Neki orok udvosseget) az utat a legkonnyebb fele"},{"SurahNumber":87,"VerseNumber":9,"Text":"Inisel hat, amig hasznal az intes"},{"SurahNumber":87,"VerseNumber":10,"Text":"Es az, aki feli az o Urat, figyelni fog az intelemre"},{"SurahNumber":87,"VerseNumber":11,"Text":"Am a legelkarhozandobb el fogja keruli azt"},{"SurahNumber":87,"VerseNumber":12,"Text":"Aki a nagy tuzon fog egni"},{"SurahNumber":87,"VerseNumber":13,"Text":"Nem fog ott meghalni, de elo sem lesz"},{"SurahNumber":87,"VerseNumber":14,"Text":"Boldogulni az fog, aki megtisztitja magat"},{"SurahNumber":87,"VerseNumber":15,"Text":"Es megemlekezik az o Ura Neverol, es elvegzi az imadsagot"},{"SurahNumber":87,"VerseNumber":16,"Text":"Am ti tobbre becsulitek az evilagi letet"},{"SurahNumber":87,"VerseNumber":17,"Text":"De a Tulvilag jobb es maradandobb"},{"SurahNumber":87,"VerseNumber":18,"Text":"Bizony, ez mar a korabbi lapokon is megtalalhato"},{"SurahNumber":87,"VerseNumber":19,"Text":"Ibrahim (Abraham) es Musu (Mozes) lapjain"},{"SurahNumber":88,"VerseNumber":1,"Text":"Elert-e hozzad a mindent Beboritonak (al-gasiyatu Feltamadas Napjanak egyik elnevezese) a tortenete"},{"SurahNumber":88,"VerseNumber":2,"Text":"Azon a Napon (a Feltamadas Napjan) nemely arcok (a hitetleneke) alazatosak lesznek"},{"SurahNumber":88,"VerseNumber":3,"Text":"— Gyotrodve igyekvok? es kifaradtak"},{"SurahNumber":88,"VerseNumber":4,"Text":"Forro tuzben fognak egni"},{"SurahNumber":88,"VerseNumber":5,"Text":"Forrasban levo forrasbol kapnak inni"},{"SurahNumber":88,"VerseNumber":6,"Text":"Csak a darf (keseru, tuskes bokor) lesz a taplalekuk"},{"SurahNumber":88,"VerseNumber":7,"Text":"Amely nem hizlal, es nem csillapszik tole az ehseg"},{"SurahNumber":88,"VerseNumber":8,"Text":"Azon a Napon, nemely arcok gyonyortol ragyogok lesznek"},{"SurahNumber":88,"VerseNumber":9,"Text":"Amelyek igyekezetuknek orvendeznek"},{"SurahNumber":88,"VerseNumber":10,"Text":"Magasan levo (vagy magasztos) Kertben (a Paradicsomban)"},{"SurahNumber":88,"VerseNumber":11,"Text":"Amelyben nem hallhato ertelmetlen, hamis beszed"},{"SurahNumber":88,"VerseNumber":12,"Text":"Patak folyik abban"},{"SurahNumber":88,"VerseNumber":13,"Text":"Magasra emelt ulohelyek lesznek abban"},{"SurahNumber":88,"VerseNumber":14,"Text":"Odarakott serlegekkel"},{"SurahNumber":88,"VerseNumber":15,"Text":"Sorba rakott parak"},{"SurahNumber":88,"VerseNumber":16,"Text":"Kiteritett diszes szonyegek"},{"SurahNumber":88,"VerseNumber":17,"Text":"Vajon nem gondolnak es nem neznek a tevere, hogyan is teremtetett"},{"SurahNumber":88,"VerseNumber":18,"Text":"Es az Egre, hogyan emeltetett"},{"SurahNumber":88,"VerseNumber":19,"Text":"Es a hegyekre, hogyan allittattak"},{"SurahNumber":88,"VerseNumber":20,"Text":"Es a Foldre, hogyan terittetett ki"},{"SurahNumber":88,"VerseNumber":21,"Text":"Figyelmeztess hat ( Muhammad- Allah aldja meg es adjon Neki orok udvosseget)! Hiszen te csak egy figyelmezteto vagy"},{"SurahNumber":88,"VerseNumber":22,"Text":"Nem birsz hatalommal felettuk"},{"SurahNumber":88,"VerseNumber":23,"Text":"Amaz, aki elfordul es hitetlenkedik"},{"SurahNumber":88,"VerseNumber":24,"Text":"Azt Allah a legnagyobb buntetessel bunteti"},{"SurahNumber":88,"VerseNumber":25,"Text":"Bizony Hozzank fognak ok visszaterni"},{"SurahNumber":88,"VerseNumber":26,"Text":"Es majdan a Mi feladatunk lesz elszamoltatni oket"},{"SurahNumber":89,"VerseNumber":1,"Text":"A hajnalhasadasra"},{"SurahNumber":89,"VerseNumber":2,"Text":"Esa tiz ejszakara"},{"SurahNumber":89,"VerseNumber":3,"Text":"A parosra es paratlanra (Allah teremteseben)"},{"SurahNumber":89,"VerseNumber":4,"Text":"Es az ejszakara, midon elmulik"},{"SurahNumber":89,"VerseNumber":5,"Text":"Vajon nincs-e esku ebben az esszel birok szamara"},{"SurahNumber":89,"VerseNumber":6,"Text":"Talan nem lattad (Muhammad- Allah aldja meg es adjon Neki orok udvosseget), hogyan cselekedett az Urad \"Ad-dal"},{"SurahNumber":89,"VerseNumber":7,"Text":"Az oszlopokkal ellatott /ram- mal"},{"SurahNumber":89,"VerseNumber":8,"Text":"Amelyhez hasonlo nem teremtetett sehol az orszagokban"},{"SurahNumber":89,"VerseNumber":9,"Text":"Es Tamiid-dal, amely kivajta! a sziklat a volgyben"},{"SurahNumber":89,"VerseNumber":10,"Text":"Es a Faraoval, a karok gazdajaval"},{"SurahNumber":89,"VerseNumber":11,"Text":"Akik tulkapasokra vetemedtek az orszagokban"},{"SurahNumber":89,"VerseNumber":12,"Text":"Es megsokszoroztak a romlast"},{"SurahNumber":89,"VerseNumber":13,"Text":"Am Urad rajuk arasztotta a kibontott buntetes ostorat"},{"SurahNumber":89,"VerseNumber":14,"Text":"Bizony a te Urad allandoan Figyelmes (veluk szemben)"},{"SurahNumber":89,"VerseNumber":15,"Text":"Am az ember, ha Ura probanak veti ala ugy, hogy nagylelku es kegyes hozza, azt mondja majd: Az Uram kegyes volt velem"},{"SurahNumber":89,"VerseNumber":16,"Text":"Am az ember, ha az Ura probanak veti ala ugy, hogy szukiti az ellatasat, azt mondja: .Megalazott az Uram"},{"SurahNumber":89,"VerseNumber":17,"Text":"Denem! Ti nem vagytok kegyesek az arvaval szemben"},{"SurahNumber":89,"VerseNumber":18,"Text":"Es nem buzditotok a szegenyek taplalasara"},{"SurahNumber":89,"VerseNumber":19,"Text":"Es mohon faljatok fel az orokseget"},{"SurahNumber":89,"VerseNumber":20,"Text":"Es vegtelenul szeretitek a vagyont"},{"SurahNumber":89,"VerseNumber":21,"Text":"Denem! Midon majd a Fold Porra toretik szet"},{"SurahNumber":89,"VerseNumber":22,"Text":"Es eljon Urad az Angyalokkal sorban"},{"SurahNumber":89,"VerseNumber":23,"Text":"Azon a Napon elohozatik a Pokol. Azon a Napon ballgatni fog az ember az intesre. De mit hasznal majd az emlekezes"},{"SurahNumber":89,"VerseNumber":24,"Text":"Azt fogja mondani: ,O, barcsak valamit (jo cselekedeteket) elore kuldtem volna az eletem szamara"},{"SurahNumber":89,"VerseNumber":25,"Text":"Es azon a Napon senki nem fog ugy buntetni, mint O"},{"SurahNumber":89,"VerseNumber":26,"Text":"Es senki nem fog ugy megbeklyozni, mint O"},{"SurahNumber":89,"VerseNumber":27,"Text":"(Az mondatik a kegyes hivonek.) O, te megnyugodott lelek"},{"SurahNumber":89,"VerseNumber":28,"Text":"Terj vissza Uradhoz elegedetten, es veled is megelegedve"},{"SurahNumber":89,"VerseNumber":29,"Text":"Lepj be az En szolgaim koze"},{"SurahNumber":89,"VerseNumber":30,"Text":"Es lepj be az En Paradicsomomba"}]}