{"Type":"ruku","Number":108,"DefaultUrl":"https://download.quranicaudio.com/quran/fares/reencode/006.mp3","TotalDurationMs":null,"Segments":[{"I":0,"S":6,"V":56,"Url":"https://download.quranicaudio.com/quran/fares/reencode/006.mp3","StartMs":909097,"EndMs":926799,"DurationMs":17702},{"I":1,"S":6,"V":57,"Url":"https://download.quranicaudio.com/quran/fares/reencode/006.mp3","StartMs":926799,"EndMs":945336,"DurationMs":18537},{"I":2,"S":6,"V":58,"Url":"https://download.quranicaudio.com/quran/fares/reencode/006.mp3","StartMs":945336,"EndMs":957773,"DurationMs":12437},{"I":3,"S":6,"V":59,"Url":"https://download.quranicaudio.com/quran/fares/reencode/006.mp3","StartMs":957773,"EndMs":984304,"DurationMs":26531},{"I":4,"S":6,"V":60,"Url":"https://download.quranicaudio.com/quran/fares/reencode/006.mp3","StartMs":984304,"EndMs":1009601,"DurationMs":25297}]}