{"Id":330,"LanguageCodes":["es","spa"],"Name":"spa-juliocortes","Author":"Julio Cortes","Language":"Spanish","Description":"Spanish","Direction":"ltr","Source":"http://tanzil.net","Translations":[{"SurahNumber":51,"VerseNumber":31,"Text":"Dijo: «¿Qué es lo que os trae, ¡enviados!?»"},{"SurahNumber":51,"VerseNumber":32,"Text":"Dijeron: «Se nos ha enviado a un pueblo pecador"},{"SurahNumber":51,"VerseNumber":33,"Text":"para enviar contra ellos piedras de barro cocido"},{"SurahNumber":51,"VerseNumber":34,"Text":"marcadas junto a tu Señor para los inmoderados»"},{"SurahNumber":51,"VerseNumber":35,"Text":"Y sacamos a los creyentes que en ella había"},{"SurahNumber":51,"VerseNumber":36,"Text":"pero sólo encontramos en ella una casa de gente sometida a Alá"},{"SurahNumber":51,"VerseNumber":37,"Text":"Y dejamos en ella un signo para los que temen el castigo doloroso"},{"SurahNumber":51,"VerseNumber":38,"Text":"Y en Moisés. Cuando le enviamos a Faraón con una autoridad manifiesta"},{"SurahNumber":51,"VerseNumber":39,"Text":"Pero, seguro de su poder, se volvió y dijo: «¡Es un mago o un poseso!»"},{"SurahNumber":51,"VerseNumber":40,"Text":"Entonces les sorprendimos, a él y a sus tropas, y los arrojamos al mar. Había incurrido en censura"},{"SurahNumber":51,"VerseNumber":41,"Text":"Y en los aditas. Cuando enviamos contra ellos el viento desvastador"},{"SurahNumber":51,"VerseNumber":42,"Text":"que pulverizaba todo cuanto encontraba a su paso"},{"SurahNumber":51,"VerseNumber":43,"Text":"Y en los tamudeos. Cuando se les dijo: «¡Gozad aún por algún tiempo!»"},{"SurahNumber":51,"VerseNumber":44,"Text":"Pero infringieron la orden de su Señor y les sorprendió el Rayo, viéndolo venir"},{"SurahNumber":51,"VerseNumber":45,"Text":"No pudieron tenerse en pie, ni defenderse"},{"SurahNumber":51,"VerseNumber":46,"Text":"Y al pueblo de Noé. Fue un pueblo perverso"},{"SurahNumber":51,"VerseNumber":47,"Text":"Y el cielo, lo construimos con fuerza. Y, ciertamente, asignamos un vasto espacio"},{"SurahNumber":51,"VerseNumber":48,"Text":"Y la tierra, la extendimos. ¡Qué bien que la preparamos"},{"SurahNumber":51,"VerseNumber":49,"Text":"Todo lo creamos por parejas. Quizás, así, os dejéis amonestar"},{"SurahNumber":51,"VerseNumber":50,"Text":"«¡Refugiaos, pues, en Alá! Soy para vosotros, de Su parte, un monitor que habla claro"},{"SurahNumber":51,"VerseNumber":51,"Text":"¡No pongáis a otro dios junto con Alá! Soy para vosotros, de Su parte, un monitor que habla claro»"},{"SurahNumber":51,"VerseNumber":52,"Text":"Asimismo, no vino a los que fueron antes ningún enviado que no dijeran: «¡Es un mago o un poseso!»"},{"SurahNumber":51,"VerseNumber":53,"Text":"¿Es que se han legado eso unos a otros? ¡No! ¡Son gente rebelde"},{"SurahNumber":51,"VerseNumber":54,"Text":"¡Apártate de ellos y, así, no incurrirás en censura"},{"SurahNumber":51,"VerseNumber":55,"Text":"¡Y amonesta, que la amonestación aprovecha a los creyentes"},{"SurahNumber":51,"VerseNumber":56,"Text":"No he creado a los genios y a los hombres sino para que Me sirvan"},{"SurahNumber":51,"VerseNumber":57,"Text":"No quiero de ellos ningún sustento, no quiero que Me alimenten"},{"SurahNumber":51,"VerseNumber":58,"Text":"Alá es el Proveedor de todo, el Fuerte, el Firme"},{"SurahNumber":51,"VerseNumber":59,"Text":"Los impíos correrán la misma suerte que corrieron sus semejantes. ¡Que no Me den, pues, prisa"},{"SurahNumber":51,"VerseNumber":60,"Text":"¡Ay de los que no creen, por el día con que se les amenaza"},{"SurahNumber":52,"VerseNumber":1,"Text":"¡Por el Monte"},{"SurahNumber":52,"VerseNumber":2,"Text":"¡Por una Escritura, puesta por escrito"},{"SurahNumber":52,"VerseNumber":3,"Text":"en un pergamino desenrollado"},{"SurahNumber":52,"VerseNumber":4,"Text":"¡Por la Casa frecuentada"},{"SurahNumber":52,"VerseNumber":5,"Text":"¡Por la bóveda elevada"},{"SurahNumber":52,"VerseNumber":6,"Text":"¡Por el mar hinchado"},{"SurahNumber":52,"VerseNumber":7,"Text":"¡Sí, el castigo de tu Señor tendrá lugar"},{"SurahNumber":52,"VerseNumber":8,"Text":"nadie podrá rechazarlo"},{"SurahNumber":52,"VerseNumber":9,"Text":"El día que el cielo gire vertiginosamente"},{"SurahNumber":52,"VerseNumber":10,"Text":"y se pongan las montañas en marcha"},{"SurahNumber":52,"VerseNumber":11,"Text":"Ese día ¡ay de los desmentidores"},{"SurahNumber":52,"VerseNumber":12,"Text":"que parloteaban por pasar el rato"},{"SurahNumber":52,"VerseNumber":13,"Text":"El día que se les empuje, violentamente, al fuego de la gehena"},{"SurahNumber":52,"VerseNumber":14,"Text":"«¡Éste es el fuego que desmentíais"},{"SurahNumber":52,"VerseNumber":15,"Text":"¿Es, pues, esto magia? ¿O es que no veis claro"},{"SurahNumber":52,"VerseNumber":16,"Text":"¡Arded en él! Debe daros lo mismo que lo aguantéis o no. Sólo se os retribuye por vuestras obras»"},{"SurahNumber":52,"VerseNumber":17,"Text":"Quienes temieron a Alá, en cambio, estarán en jardines y delicia"},{"SurahNumber":52,"VerseNumber":18,"Text":"disfrutando de lo que su Señor les dé. Su Señor les habrá preservado del castigo del fuego de la gehena"},{"SurahNumber":52,"VerseNumber":19,"Text":"«¡Comed y bebed en paz! ¡Por lo que habéis hecho!»"},{"SurahNumber":52,"VerseNumber":20,"Text":"Reclinados en lechos alineados. Y les daremos por esposas a huríes de grandes ojos"},{"SurahNumber":52,"VerseNumber":21,"Text":"Reuniremos con los creyentes a los descendientes que les siguieron en la fe. No les menoscabaremos nada sus obras. Cada uno será responsable de lo que haya cometido"},{"SurahNumber":52,"VerseNumber":22,"Text":"Les proveeremos de la fruta y de la carne que apetezcan"},{"SurahNumber":52,"VerseNumber":23,"Text":"Allí se pasarán unos a otros una copa cuyo contenido no incitará a vaniloquio ni a pecado"},{"SurahNumber":52,"VerseNumber":24,"Text":"Para servirles, circularán a su alrededor muchachos como perlas ocultas"},{"SurahNumber":52,"VerseNumber":25,"Text":"Y se volverán unos a otros para preguntarse"},{"SurahNumber":52,"VerseNumber":26,"Text":"Dirán: «Antes vivíamos angustiados en medio de nuestra familia"},{"SurahNumber":52,"VerseNumber":27,"Text":"Alá nos agració y preservó del castigo del viento abrasador"},{"SurahNumber":52,"VerseNumber":28,"Text":"Ya Le invocábamos antes. Es el Bueno, el Misericordioso»"},{"SurahNumber":52,"VerseNumber":29,"Text":"¡Amonesta, pues, porque, por la gracia de tu Señor, no eres adivino ni poseso"},{"SurahNumber":52,"VerseNumber":30,"Text":"O dicen: «¡Un poeta...! ¡Esperaremos las vicisitudes de su sino!»"},{"SurahNumber":52,"VerseNumber":31,"Text":"Di: «¡Esperad! Yo espero con vosotros»"},{"SurahNumber":52,"VerseNumber":32,"Text":"¿Se les ordena en sueños que hablen así o es que son gente rebelde"},{"SurahNumber":52,"VerseNumber":33,"Text":"O dicen: «¡Él se lo ha inventado!» ¡No, no creen"},{"SurahNumber":52,"VerseNumber":34,"Text":"Si es verdad lo que dicen, ¡que traigan un relato semejante"},{"SurahNumber":52,"VerseNumber":35,"Text":"¿Han sido creados de la nada? ¿O son ellos los creadores"},{"SurahNumber":52,"VerseNumber":36,"Text":"¿O han creado los cielos y la tierra? No, no están convencidos"},{"SurahNumber":52,"VerseNumber":37,"Text":"¿O tienen los tesoros de tu Señor? ¿O se creen unos potentados"},{"SurahNumber":52,"VerseNumber":38,"Text":"¿O tienen una escala que les permita escuchar? El que de ellos lo consiga ¡que aporte una autoridad manifesta"},{"SurahNumber":52,"VerseNumber":39,"Text":"¿O tendrá Él hijas, como vosotros tenéis hijos"},{"SurahNumber":52,"VerseNumber":40,"Text":"¿O es que les reclamas un salario tal que se vean abrumados de deudas"},{"SurahNumber":52,"VerseNumber":41,"Text":"¿O es que conocen lo oculto y toman nota"},{"SurahNumber":52,"VerseNumber":42,"Text":"¿O quieren urdir una estratagema? Los infieles serían sus víctimas"},{"SurahNumber":52,"VerseNumber":43,"Text":"¿O tienen un dios diferente de Alá? ¡Gloria a Alá, Que está por encima de lo que Le asocian"},{"SurahNumber":52,"VerseNumber":44,"Text":"Si vieran caer parte del cielo, dirían: «Son nubes que se han amontonado»"},{"SurahNumber":52,"VerseNumber":45,"Text":"Déjales hasta que les llegue su día, cuando sean fulminados"},{"SurahNumber":52,"VerseNumber":46,"Text":"el día de su estratagema no les sirva de nada y nadie les auxilie"},{"SurahNumber":52,"VerseNumber":47,"Text":"Los impíos sufrirán, además, otro castigo, pero la mayoría no saben"},{"SurahNumber":52,"VerseNumber":48,"Text":"¡Espera paciente la decisión de tu, Señor, pues te vemos! Y ¡celebra las alabanzas de tu Señor cuando estás de pie"},{"SurahNumber":52,"VerseNumber":49,"Text":"¡Glorifícale durante la noche y al declinar las estrellas"},{"SurahNumber":53,"VerseNumber":1,"Text":"¡Por la estrella, cuando declina"},{"SurahNumber":53,"VerseNumber":2,"Text":"Vuestro paisano no se extravía, ni se descarría"},{"SurahNumber":53,"VerseNumber":3,"Text":"No habla por propio impulso"},{"SurahNumber":53,"VerseNumber":4,"Text":"No es sino una revelación que se ha hecho"},{"SurahNumber":53,"VerseNumber":5,"Text":"Se la ha enseñado el muy poderoso"},{"SurahNumber":53,"VerseNumber":6,"Text":"fuerte, majestuoso"},{"SurahNumber":53,"VerseNumber":7,"Text":"mientras él estaba en lo más alto del horizonte"},{"SurahNumber":53,"VerseNumber":8,"Text":"Luego, se acercó y quedó suspendido en el aire"},{"SurahNumber":53,"VerseNumber":9,"Text":"estaba a dos medidas de arco o menos"},{"SurahNumber":53,"VerseNumber":10,"Text":"Reveló a Su siervo lo que reveló"},{"SurahNumber":53,"VerseNumber":11,"Text":"No ha mentido el corazón en lo que vio"},{"SurahNumber":53,"VerseNumber":12,"Text":"¿Disputaréis, pues, con él sobre lo que ve"},{"SurahNumber":53,"VerseNumber":13,"Text":"Ya le había visto descender en otra ocasión"},{"SurahNumber":53,"VerseNumber":14,"Text":"junto al azufaifo del confín"},{"SurahNumber":53,"VerseNumber":15,"Text":"junto al cual se encuentra el jardín de la Morada"},{"SurahNumber":53,"VerseNumber":16,"Text":"cuando el azufaifo estaba cubierto por aquello"},{"SurahNumber":53,"VerseNumber":17,"Text":"No se desvió la mirada. Y no erró"},{"SurahNumber":53,"VerseNumber":18,"Text":"Vio, ciertamente, parte de los signos tan grandes de su Señor"},{"SurahNumber":53,"VerseNumber":19,"Text":"Y ¿qué os parecen al-Lat, al-Uzza"},{"SurahNumber":53,"VerseNumber":20,"Text":"y la otra, Manat, la tercera"},{"SurahNumber":53,"VerseNumber":21,"Text":"¿Para vosotros los varones y para Él las hembras"},{"SurahNumber":53,"VerseNumber":22,"Text":"Sería un reparto injusto"},{"SurahNumber":53,"VerseNumber":23,"Text":"No son sino nombres que habéis puesto, vosotros y vuestros padres, a los que Alá no ha conferido ninguna autoridad. No siguen sino conjeturas y la concupiscencia de sus almas, siendo así que ya les ha venido de su Señor la Dirección"},{"SurahNumber":53,"VerseNumber":24,"Text":"¿Obtendrá el hombre lo que desea"},{"SurahNumber":53,"VerseNumber":25,"Text":"Pero la otra vida y esta vida pertenecen a Alá"},{"SurahNumber":53,"VerseNumber":26,"Text":"¡Cuántos ángeles hay en los cielos, cuya intercesión no servirá de nada, a menos que antes dé Alá permiso a quien Él quiera, a quien Le plazca"},{"SurahNumber":53,"VerseNumber":27,"Text":"Quienes no creen en la otra vida ponen, sí, a los ángeles nombres femeninos"},{"SurahNumber":53,"VerseNumber":28,"Text":"No tienen ningún conocimiento de ello. No siguen más que conjeturas, y éstas, frente a la Verdad, no sirven de nada"},{"SurahNumber":53,"VerseNumber":29,"Text":"Apártate de quien vuelve la espalda a Nuestra Amonestación y no desea sino la vida de acá"},{"SurahNumber":53,"VerseNumber":30,"Text":"Ésa es toda la ciencia que pueden alcanzar. Alá conoce bien a quien se extravía de Su camino y conoce bien a quien sigue la buena dirección"},{"SurahNumber":53,"VerseNumber":31,"Text":"De Alá es lo que está en los cielos y en la tierra, para retribuir a los que obren mal por lo que hagan y retribuir a los que obren bien dándoles lo mejor"},{"SurahNumber":53,"VerseNumber":32,"Text":"Quienes evitan los pecados graves y las deshonestidades y sólo cometen pecados leves... Tu Señor es inmensamente indulgente. Os conocía bien cuando os creaba de la tierra y cuando erais un embrión en el seno de vuestra madre. ¡No os jactéis, pues, de puros! Él conoce bien a los que Le temen"},{"SurahNumber":53,"VerseNumber":33,"Text":"Y, ¿qué te parece el que vuelve la espalda"},{"SurahNumber":53,"VerseNumber":34,"Text":"Da poco, es mezquino"},{"SurahNumber":53,"VerseNumber":35,"Text":"¿Tiene la ciencia de lo oculto, que le permita ver"},{"SurahNumber":53,"VerseNumber":36,"Text":"¿No se le ha informado del contenido de las Hojas de Moisés"},{"SurahNumber":53,"VerseNumber":37,"Text":"y de Abraham, que cumplió"},{"SurahNumber":53,"VerseNumber":38,"Text":"que nadie cargará con la carga ajena"},{"SurahNumber":53,"VerseNumber":39,"Text":"que el hombre sólo será sancionado con arreglo a su propio esfuerzo"},{"SurahNumber":53,"VerseNumber":40,"Text":"que se verá el resultado de su esfuerzo"},{"SurahNumber":53,"VerseNumber":41,"Text":"que será, luego, retribuido generosamente"},{"SurahNumber":53,"VerseNumber":42,"Text":"que el fin de todo es tu Señor"},{"SurahNumber":53,"VerseNumber":43,"Text":"que es Él Quien hace reír y hace llorar"},{"SurahNumber":53,"VerseNumber":44,"Text":"que es Él Quien da la muerte y da la vida"},{"SurahNumber":53,"VerseNumber":45,"Text":"que Él crea la pareja, varón y hembra"},{"SurahNumber":53,"VerseNumber":46,"Text":"de una gota cuando es eyaculada"},{"SurahNumber":53,"VerseNumber":47,"Text":"que a Él incumbe la otra creación"},{"SurahNumber":53,"VerseNumber":48,"Text":"que es Él Quien da riquezas y posesiones"},{"SurahNumber":53,"VerseNumber":49,"Text":"que es Él el Señor de Sirio"},{"SurahNumber":53,"VerseNumber":50,"Text":"que Él hizo perecer a los antiguos aditas"},{"SurahNumber":53,"VerseNumber":51,"Text":"y a los tamudeos, sin dejar uno solo con vida"},{"SurahNumber":53,"VerseNumber":52,"Text":"y, antes, al pueblo de Noé, que fue tan impío y rebelde"},{"SurahNumber":53,"VerseNumber":53,"Text":"y aniquiló a la vuelta de arriba abajo"},{"SurahNumber":53,"VerseNumber":54,"Text":"cubriéndola como la cubrió"},{"SurahNumber":53,"VerseNumber":55,"Text":"¿Cuál, pues, de los beneficios de tu Señor pondrás en duda"},{"SurahNumber":53,"VerseNumber":56,"Text":"Ésta es una advertencia al estilo de las advertencias antiguas"},{"SurahNumber":53,"VerseNumber":57,"Text":"Amenaza la Inminente"},{"SurahNumber":53,"VerseNumber":58,"Text":"Nadie, fuera de Alá, puede quitarla"},{"SurahNumber":53,"VerseNumber":59,"Text":"¿Os asombráis, pues, de este discurso"},{"SurahNumber":53,"VerseNumber":60,"Text":"¿Y reís, en lugar de llorar"},{"SurahNumber":53,"VerseNumber":61,"Text":"permaneciendo indiferentes"},{"SurahNumber":53,"VerseNumber":62,"Text":"¡Prosternaos, pues, ante Alá y servidle"},{"SurahNumber":54,"VerseNumber":1,"Text":"Se acerca la Hora, se hiende la luna"},{"SurahNumber":54,"VerseNumber":2,"Text":"Si ven un signo, se apartan y dicen: «¡Es una magia continua!»"},{"SurahNumber":54,"VerseNumber":3,"Text":"Desmienten y siguen sus pasiones. Pero todo está decretado"},{"SurahNumber":54,"VerseNumber":4,"Text":"Ya han recibido noticias disuasivas"},{"SurahNumber":54,"VerseNumber":5,"Text":"consumada sabiduría. Pero las advertencias no sirven"},{"SurahNumber":54,"VerseNumber":6,"Text":"¡Apártate, pues, de ellos! El día que el Pregonero les convoque para algo horrible"},{"SurahNumber":54,"VerseNumber":7,"Text":"abatida la mirada, saldrán de las sepulturas como si fueran langostas esparcidas"},{"SurahNumber":54,"VerseNumber":8,"Text":"corriendo con el cuello extendido hacia el Pregonero. Dirán los infieles: «¡Éste es un día difícil!»"},{"SurahNumber":54,"VerseNumber":9,"Text":"Antes de ello, ya el pueblo de Noé había desmentido. Desmintieron a Nuestro siervo y dijeron: «¡Un poseso!», y fue rechazado"},{"SurahNumber":54,"VerseNumber":10,"Text":"Entonces, invocó a su Señor. «¡Estoy vencido! ¡Defiéndete!»"},{"SurahNumber":54,"VerseNumber":11,"Text":"Abrimos las puertas del cielo a una lluvia torrencial"},{"SurahNumber":54,"VerseNumber":12,"Text":"y en la tierra hicimos manar fuentes. Y el agua se encontró según una orden decretada"},{"SurahNumber":54,"VerseNumber":13,"Text":"Le embarcamos en aquello de planchas y de fibras"},{"SurahNumber":54,"VerseNumber":14,"Text":"que navegó bajo Nuestra mirada como retribución de aquél que había sido negado"},{"SurahNumber":54,"VerseNumber":15,"Text":"La dejamos como signo. Pero ¿hay alguien que se deje amonestar"},{"SurahNumber":54,"VerseNumber":16,"Text":"Y ¡cuáles no fueron Mi castigo y Mis advertencias"},{"SurahNumber":54,"VerseNumber":17,"Text":"Hemos facilitado el Corán para que pueda servir de amonestación. Pero ¿hay alguien que se deje amonestar"},{"SurahNumber":54,"VerseNumber":18,"Text":"Los aditas desmintieron y ¡cuáles no fueron Mi castigo y Mis advertencias"},{"SurahNumber":54,"VerseNumber":19,"Text":"En un día nefasto e interminable enviamos contra ellos un viento glacial"},{"SurahNumber":54,"VerseNumber":20,"Text":"que arrancaba a los hombres como si hubieran sido troncos de palmeras descuajadas"},{"SurahNumber":54,"VerseNumber":21,"Text":"Y ¡cuáles no fueron Mi castigo y Mis advertencias"},{"SurahNumber":54,"VerseNumber":22,"Text":"Hemos facilitado el Corán para que pueda servir de amonestación. Pero ¿hay alguien que se deje amonestar"},{"SurahNumber":54,"VerseNumber":23,"Text":"Los tamudeos desmintieron las advertencias"},{"SurahNumber":54,"VerseNumber":24,"Text":"y dijeron: «¿Vamos a seguir a un solo mortal, salido de nosotros? ¡Estaríamos extraviados y deliraríamos"},{"SurahNumber":54,"VerseNumber":25,"Text":"¿A él, entre nosotros, se le iba a confiar la Amonestación? ¡No, sino que es un mentiroso, un insolente!»"},{"SurahNumber":54,"VerseNumber":26,"Text":"¡Mañana verán quién es el mentiroso, el insolente"},{"SurahNumber":54,"VerseNumber":27,"Text":"Vamos a enviarles la camella para tentarles. ¡Obsérvales y ten paciencia"},{"SurahNumber":54,"VerseNumber":28,"Text":"Infórmales de que el agua debe repartirse entre ellos y de que beberán por turno"},{"SurahNumber":54,"VerseNumber":29,"Text":"Llamaron a su paisano, que se hizo cargo y desjarretó"},{"SurahNumber":54,"VerseNumber":30,"Text":"Y ¡cuáles no fueron Mi castigo y Mis advertencias"},{"SurahNumber":54,"VerseNumber":31,"Text":"Les lanzamos un solo Grito y fueron como hierba seca que se emplea para levantar una cerca"},{"SurahNumber":54,"VerseNumber":32,"Text":"Hemos facilitado el Corán para que pueda servir de amonestación. Pero ¿hay alguien que se deje amonestar"},{"SurahNumber":54,"VerseNumber":33,"Text":"El pueblo de Lot desmintió las advertencias"},{"SurahNumber":54,"VerseNumber":34,"Text":"Enviamos contra ellos una tempestad de arena. Exceptuamos a la familia de Lot, a la que salvamos al rayar el alba"},{"SurahNumber":54,"VerseNumber":35,"Text":"en virtud de una gracia venida de Nosotros. Así retribuimos al agradecido"},{"SurahNumber":54,"VerseNumber":36,"Text":"Les había prevenido contra Nuestro rigor, pero pusieron en duda las advertencias"},{"SurahNumber":54,"VerseNumber":37,"Text":"Le exigieron a sus huéspedes y les apagamos los ojos. «¡Gustad Mi castigo y Mis advertencias!»"},{"SurahNumber":54,"VerseNumber":38,"Text":"A la mañana siguiente, temprano, les sorprendió un castigo duradero"},{"SurahNumber":54,"VerseNumber":39,"Text":"«¡Gustad Mi castigo y Mis advertencias!»"},{"SurahNumber":54,"VerseNumber":40,"Text":"Hemos facilitado el Corán para que pueda servir de amonestación. Pero ¿hay alguien que se deje amonestar"},{"SurahNumber":54,"VerseNumber":41,"Text":"Y, ciertamente, la gente de Faraón fue advertida"},{"SurahNumber":54,"VerseNumber":42,"Text":"Desmintieron todos Nuestros signos y les sorprendimos como sorprende Uno poderoso, potísimo"},{"SurahNumber":54,"VerseNumber":43,"Text":"¿Son vuestros infieles mejores que aquéllos? ¿O hay en las Escrituras algo que os inmunice"},{"SurahNumber":54,"VerseNumber":44,"Text":"¿O dicen: «Somos un conjunto capaz de defenderse»"},{"SurahNumber":54,"VerseNumber":45,"Text":"Todos serán derrotados y huirán"},{"SurahNumber":54,"VerseNumber":46,"Text":"Pero la Hora es el tiempo que se les ha fijado y la Hora es crudelísima, amarguísima"},{"SurahNumber":54,"VerseNumber":47,"Text":"Los pecadores están extraviados y deliran"},{"SurahNumber":54,"VerseNumber":48,"Text":"El día que sean arrastrados boca abajo al Fuego: «¡Gustad el contacto del saqar !»"},{"SurahNumber":54,"VerseNumber":49,"Text":"Todo lo hemos creado con medida"},{"SurahNumber":54,"VerseNumber":50,"Text":"Nuestra orden no consiste sino en una sola palabra, como un abrir y cerrar de ojos"},{"SurahNumber":54,"VerseNumber":51,"Text":"Hemos hecho perecer a vuestros semejantes. Pero ¿hay alguien que se deje amonestar"},{"SurahNumber":54,"VerseNumber":52,"Text":"Todo lo que han hecho consta en las Escrituras"},{"SurahNumber":54,"VerseNumber":53,"Text":"Todo, grande o pequeño, está con signado"},{"SurahNumber":54,"VerseNumber":54,"Text":"Los temerosos de Alá estarán entre jardines y arroyos"},{"SurahNumber":54,"VerseNumber":55,"Text":"en una sede buena, junto a un potísimo Monarca"},{"SurahNumber":55,"VerseNumber":1,"Text":"El Compasivo"},{"SurahNumber":55,"VerseNumber":2,"Text":"ha enseñado el Corán"},{"SurahNumber":55,"VerseNumber":3,"Text":"Ha creado al hombre"},{"SurahNumber":55,"VerseNumber":4,"Text":"le ha enseñado a explicar"},{"SurahNumber":55,"VerseNumber":5,"Text":"El sol y la luna, para cómputo"},{"SurahNumber":55,"VerseNumber":6,"Text":"Las hierbas y los árboles se prosternan"},{"SurahNumber":55,"VerseNumber":7,"Text":"Ha elevado el cielo. Ha establecido la balanza"},{"SurahNumber":55,"VerseNumber":8,"Text":"para que no faltéis al peso"},{"SurahNumber":55,"VerseNumber":9,"Text":"sino que deis la pesada equitativa, sin defraudar en el peso"},{"SurahNumber":55,"VerseNumber":10,"Text":"La tierra la ha puesto al servicio de las criaturas"},{"SurahNumber":55,"VerseNumber":11,"Text":"Hay en ella fruta y palmeras de fruto recubierto"},{"SurahNumber":55,"VerseNumber":12,"Text":"grano de vaina, plantas aromáticas"},{"SurahNumber":55,"VerseNumber":13,"Text":"¿Cuál, pues, de los beneficios de vuestro Señor negaréis"},{"SurahNumber":55,"VerseNumber":14,"Text":"Creó al hombre de arcilla, como la cerámica"},{"SurahNumber":55,"VerseNumber":15,"Text":"y creó a los genios de fuego puro"},{"SurahNumber":55,"VerseNumber":16,"Text":"¿Cuál, pues, de los beneficios de vuestro Señor negaréis"},{"SurahNumber":55,"VerseNumber":17,"Text":"Señor de los dos Orientes y Señor de los dos Occidentes"},{"SurahNumber":55,"VerseNumber":18,"Text":"¿Cuál, pues, de los beneficios de vuestro Señor negaréis"},{"SurahNumber":55,"VerseNumber":19,"Text":"Ha dejado fluir las dos grandes masas de agua, que se encuentran"},{"SurahNumber":55,"VerseNumber":20,"Text":"pero las separa una barrera que no rebasan"},{"SurahNumber":55,"VerseNumber":21,"Text":"¿Cuál, pues, de los beneficios de vuestro Señor negaréis"},{"SurahNumber":55,"VerseNumber":22,"Text":"De ambas provienen la perla y el coral"},{"SurahNumber":55,"VerseNumber":23,"Text":"¿Cuál, pues, de los beneficios de vuestro Señor negaréis"},{"SurahNumber":55,"VerseNumber":24,"Text":"Suyas son las embarcaciones, que sobresalen en el mar como mojones"},{"SurahNumber":55,"VerseNumber":25,"Text":"¿Cuál, pues, de los beneficios de vuestro Señor negaréis"},{"SurahNumber":55,"VerseNumber":26,"Text":"Todo aquél que está sobre ella es perecedero"},{"SurahNumber":55,"VerseNumber":27,"Text":"Pero subsiste tu Señor, el Majestuoso y Honorable"},{"SurahNumber":55,"VerseNumber":28,"Text":"¿Cuál, pues, de los beneficios de vuestro Señor negaréis"},{"SurahNumber":55,"VerseNumber":29,"Text":"Los que están en los cielos y en la tierra Le imploran. Siempre está ocupado en algo"},{"SurahNumber":55,"VerseNumber":30,"Text":"¿Cuál, pues, de los beneficios de vuestro Señor negaréis"},{"SurahNumber":55,"VerseNumber":31,"Text":"Nos ocuparemos detenidamente de vosotros, dos cargas"},{"SurahNumber":55,"VerseNumber":32,"Text":"¿Cuál, pues, de los beneficios de vuestro Señor negaréis"},{"SurahNumber":55,"VerseNumber":33,"Text":"¡Compañía de genios y de hombres! ¡Atravesad, si podéis, las regiones celestiales y terrestres! Pero no podréis atravesarlas sin ayuda de una autoridad"},{"SurahNumber":55,"VerseNumber":34,"Text":"¿Cuál, pues, de los beneficios de vuestro Señor negaréis"},{"SurahNumber":55,"VerseNumber":35,"Text":"Serán lanzadas contra vosotros llamaradas de fuego sin humo y de bronce fundido, y no podréis defenderos"},{"SurahNumber":55,"VerseNumber":36,"Text":"¿Cuál, pues, de los beneficios de vuestro Señor negaréis"},{"SurahNumber":55,"VerseNumber":37,"Text":"Cuando el cielo se hienda y se tiña de rojo coriáceo"},{"SurahNumber":55,"VerseNumber":38,"Text":"¿cuál, pues, de los beneficios de vuestro Señor negaréis"},{"SurahNumber":55,"VerseNumber":39,"Text":"ese día, ni los hombres ni los genios serán interrogados acerca de su pecado"},{"SurahNumber":55,"VerseNumber":40,"Text":"¿Cuál, pues, de los beneficios de vuestro Señor negaréis"},{"SurahNumber":55,"VerseNumber":41,"Text":"Los pecadores serán reconocidos por sus rasgos y se les cogerá por el copete y por los pies"},{"SurahNumber":55,"VerseNumber":42,"Text":"¿Cuál, pues, de los beneficios de vuestro Señor negaréis"},{"SurahNumber":55,"VerseNumber":43,"Text":"¡Ésa es la gehena que los pecadores desmentían"},{"SurahNumber":55,"VerseNumber":44,"Text":"No pararán de ir y venir entre ella y el agua muy caliente"},{"SurahNumber":55,"VerseNumber":45,"Text":"¿Cuál, pues, de los beneficios de vuestro Señor negaréis"},{"SurahNumber":55,"VerseNumber":46,"Text":"Para quien, en cambio, haya temido comparecer ante su Señor. habrá dos jardines"},{"SurahNumber":55,"VerseNumber":47,"Text":"¿cuál. pues, de los beneficios de vuestro Señor negaréis"},{"SurahNumber":55,"VerseNumber":48,"Text":"frondosos"},{"SurahNumber":55,"VerseNumber":49,"Text":"¿cuál, pues, de los beneficios de vuestro Señor negaréis"},{"SurahNumber":55,"VerseNumber":50,"Text":"con dos fuentes manando"},{"SurahNumber":55,"VerseNumber":51,"Text":"¿Cuál, pues, de los beneficios de vuestro Señor negaréis"},{"SurahNumber":55,"VerseNumber":52,"Text":"En ellos habrá dos especies de cada fruta"},{"SurahNumber":55,"VerseNumber":53,"Text":"¿Cuál, pues, de los beneficios de vuestro Señor negaréis"},{"SurahNumber":55,"VerseNumber":54,"Text":"Estarán reclinados en alfombras forradas de brocado. Tendrán a su alcance la fruta de los dos jardines"},{"SurahNumber":55,"VerseNumber":55,"Text":"¿Cuál, pues, de los beneficios de vuestro Señor negaréis"},{"SurahNumber":55,"VerseNumber":56,"Text":"Estarán en ellos las de recatado mirar, no tocadas hasta entonces por hombre ni genio"},{"SurahNumber":55,"VerseNumber":57,"Text":"¿cuál, pues, de los beneficios de vuestro Señor negaréis"},{"SurahNumber":55,"VerseNumber":58,"Text":"cual jacinto y coral"},{"SurahNumber":55,"VerseNumber":59,"Text":"¿Cuál, pues, de los beneficios de vuestro Señor negaréis"},{"SurahNumber":55,"VerseNumber":60,"Text":"La retribución del bien obrar ¿es otra que el mismo bien obrar"},{"SurahNumber":55,"VerseNumber":61,"Text":"¿Cuál, pues, de los beneficios de vuestro Señor negaréis"},{"SurahNumber":55,"VerseNumber":62,"Text":"Además de esos dos, habrá otros dos jardines"},{"SurahNumber":55,"VerseNumber":63,"Text":"¿cuál, pues, de los beneficios de vuestro Señor negaréis"},{"SurahNumber":55,"VerseNumber":64,"Text":"verdinegros"},{"SurahNumber":55,"VerseNumber":65,"Text":"¿cuál, pues, de los beneficios de vuestro Señor negaréis"},{"SurahNumber":55,"VerseNumber":66,"Text":"con dos fuentes abundantes"},{"SurahNumber":55,"VerseNumber":67,"Text":"¿Cuál, pues, de los beneficios de vuestro Señor negaréis"},{"SurahNumber":55,"VerseNumber":68,"Text":"En ambos habrá fruta, palmeras y granados"},{"SurahNumber":55,"VerseNumber":69,"Text":"¿cuál, pues, de los beneficios de vuestro Señor negaréis"},{"SurahNumber":55,"VerseNumber":70,"Text":"en ellos habrá buenas, bellas"},{"SurahNumber":55,"VerseNumber":71,"Text":"¿cuál, pues, de los beneficios de vuestro Señor negaréis"},{"SurahNumber":55,"VerseNumber":72,"Text":"huríes, retiradas en los pabellones"},{"SurahNumber":55,"VerseNumber":73,"Text":"¿cuál, pues, de los beneficios de vuestro Señor negaréis"},{"SurahNumber":55,"VerseNumber":74,"Text":"no tocadas hasta entonces por hombre ni genio"},{"SurahNumber":55,"VerseNumber":75,"Text":"¿Cuál, pues, de los beneficios de vuestro Señor negaréis"},{"SurahNumber":55,"VerseNumber":76,"Text":"Reclinados en cojines verdes y bellas alfombras"},{"SurahNumber":55,"VerseNumber":77,"Text":"¿Cuál, pues, de los beneficios de vuestro Señor negaréis"},{"SurahNumber":55,"VerseNumber":78,"Text":"¡Bendito sea el nombre de tu Señor, el Majestuoso y Honorable"},{"SurahNumber":56,"VerseNumber":1,"Text":"Cuando suceda el Acontecimiento"},{"SurahNumber":56,"VerseNumber":2,"Text":"nadie podrá negarlo"},{"SurahNumber":56,"VerseNumber":3,"Text":"¡Abatirá, exaltará"},{"SurahNumber":56,"VerseNumber":4,"Text":"Cuando la tierra sufra una violenta sacudida"},{"SurahNumber":56,"VerseNumber":5,"Text":"y las montañas sean totalmente desmenuzadas"},{"SurahNumber":56,"VerseNumber":6,"Text":"convirtiéndose en fino polvo disperso"},{"SurahNumber":56,"VerseNumber":7,"Text":"y seáis divididos en tres grupos"},{"SurahNumber":56,"VerseNumber":8,"Text":"Los de la derecha -¿qué son los de la derecha"},{"SurahNumber":56,"VerseNumber":9,"Text":"los de la izquierda -¿qué son los de la izquierda"},{"SurahNumber":56,"VerseNumber":10,"Text":"y los más distinguidos, que son los más distinguidos"},{"SurahNumber":56,"VerseNumber":11,"Text":"Éstos son los allegados"},{"SurahNumber":56,"VerseNumber":12,"Text":"en los jardines de la Delicia"},{"SurahNumber":56,"VerseNumber":13,"Text":"Habrá muchos de los primeros"},{"SurahNumber":56,"VerseNumber":14,"Text":"y pocos de los últimos"},{"SurahNumber":56,"VerseNumber":15,"Text":"En lechos entretejidos de oro y piedras preciosas"},{"SurahNumber":56,"VerseNumber":16,"Text":"reclinados en ellos, unos enfrente de otros"},{"SurahNumber":56,"VerseNumber":17,"Text":"Circularán entre ellos jóvenes criados de eterna juventud"},{"SurahNumber":56,"VerseNumber":18,"Text":"con cálices. jarros y una copa de agua viva"},{"SurahNumber":56,"VerseNumber":19,"Text":"que no les dará dolor de cabeza ni embriagará"},{"SurahNumber":56,"VerseNumber":20,"Text":"con fruta que ellos escogerán"},{"SurahNumber":56,"VerseNumber":21,"Text":"con la carne de ave que les apetezca"},{"SurahNumber":56,"VerseNumber":22,"Text":"Habrá huríes de grandes ojos"},{"SurahNumber":56,"VerseNumber":23,"Text":"semejantes a perlas ocultas"},{"SurahNumber":56,"VerseNumber":24,"Text":"como retribución a sus obras"},{"SurahNumber":56,"VerseNumber":25,"Text":"No oirán allí vaniloquio ni incitación al pecado"},{"SurahNumber":56,"VerseNumber":26,"Text":"sino una palabra: «¡Paz! ¡Paz!»"},{"SurahNumber":56,"VerseNumber":27,"Text":"Los de la derecha -¿qué son los de la derecha"},{"SurahNumber":56,"VerseNumber":28,"Text":"estarán entre azufaifos sin espinas"},{"SurahNumber":56,"VerseNumber":29,"Text":"y liños de acacias"},{"SurahNumber":56,"VerseNumber":30,"Text":"en una extensa sombra"},{"SurahNumber":56,"VerseNumber":31,"Text":"cerca de agua corriente"},{"SurahNumber":56,"VerseNumber":32,"Text":"y abundante fruta"},{"SurahNumber":56,"VerseNumber":33,"Text":"inagotable y permitida"},{"SurahNumber":56,"VerseNumber":34,"Text":"en lechos elevados"},{"SurahNumber":56,"VerseNumber":35,"Text":"Nosotros las hemos formado de manera especial"},{"SurahNumber":56,"VerseNumber":36,"Text":"y hecho vírgenes"},{"SurahNumber":56,"VerseNumber":37,"Text":"afectuosas, de una misma edad"},{"SurahNumber":56,"VerseNumber":38,"Text":"para los de la derecha"},{"SurahNumber":56,"VerseNumber":39,"Text":"Habrá muchos de los primeros"},{"SurahNumber":56,"VerseNumber":40,"Text":"y muchos de los últimos"},{"SurahNumber":56,"VerseNumber":41,"Text":"Los de la izquierda -¿qué son los de la izquierda"},{"SurahNumber":56,"VerseNumber":42,"Text":"estarán expuestos a un viento abrasador, en agua muy caliente"},{"SurahNumber":56,"VerseNumber":43,"Text":"a la sombra de un humo negro"},{"SurahNumber":56,"VerseNumber":44,"Text":"ni fresca ni agradable"},{"SurahNumber":56,"VerseNumber":45,"Text":"Antes, estuvieron rodeados de lujo"},{"SurahNumber":56,"VerseNumber":46,"Text":"sin salir del enorme pecado"},{"SurahNumber":56,"VerseNumber":47,"Text":"Decían: «Cuando muramos y seamos tierra y huesos, ¿se nos resucitará acaso"},{"SurahNumber":56,"VerseNumber":48,"Text":"¿Y también a nuestros antepasados?»"},{"SurahNumber":56,"VerseNumber":49,"Text":"Di: «¡En verdad, los primeros y los últimos"},{"SurahNumber":56,"VerseNumber":50,"Text":"serán reunidos en el momento fijado de un día determinado!»"},{"SurahNumber":56,"VerseNumber":51,"Text":"Luego, vosotros, extraviados, desmentidores"},{"SurahNumber":56,"VerseNumber":52,"Text":"comeréis, sí, de un árbol, del Zaqqum"},{"SurahNumber":56,"VerseNumber":53,"Text":"de cuyos frutos llenaréis el vientre"},{"SurahNumber":56,"VerseNumber":54,"Text":"Y, además, beberéis agua muy caliente"},{"SurahNumber":56,"VerseNumber":55,"Text":"sedientos como camellos que mueren de sed"},{"SurahNumber":56,"VerseNumber":56,"Text":"Ese será su alojamiento el día del Juicio"},{"SurahNumber":56,"VerseNumber":57,"Text":"Nosotros os creamos. ¿Por qué, pues, no aceptáis"},{"SurahNumber":56,"VerseNumber":58,"Text":"Y ¿qué os parece el semen que eyaculáis"},{"SurahNumber":56,"VerseNumber":59,"Text":"¿Lo creáis vosotros o somos Nosotros los creadores"},{"SurahNumber":56,"VerseNumber":60,"Text":"Nosotros hemos determinado que muráis y nadie podrá escapársenos"},{"SurahNumber":56,"VerseNumber":61,"Text":"para que otros seres semejantes os sucedan y haceros renacer a un estado que no conocéis"},{"SurahNumber":56,"VerseNumber":62,"Text":"Ya habéis conocido una primera creación. ¿Por qué, pues, no os dejáis amonestar"},{"SurahNumber":56,"VerseNumber":63,"Text":"Y ¿qué os parece vuestra siembra"},{"SurahNumber":56,"VerseNumber":64,"Text":"¿La sembráis vosotros o somos Nosotros los sembradores"},{"SurahNumber":56,"VerseNumber":65,"Text":"Si quisiéramos, de vuestro campo haríamos paja seca e iríais lamentándoos"},{"SurahNumber":56,"VerseNumber":66,"Text":"«Estamos abrumados de deudas"},{"SurahNumber":56,"VerseNumber":67,"Text":"más aún, se nos ha despojado»"},{"SurahNumber":56,"VerseNumber":68,"Text":"Y ¿qué os parece el agua que bebéis"},{"SurahNumber":56,"VerseNumber":69,"Text":"¿La hacéis bajar de las nubes vosotros o somos Nosotros Quienes la hacen bajar"},{"SurahNumber":56,"VerseNumber":70,"Text":"Si hubiéramos querido, la habríamos hecho salobre. ¿Por qué, pues, no dais las gracias"},{"SurahNumber":56,"VerseNumber":71,"Text":"Y ¿qué os parece el fuego que encendéis"},{"SurahNumber":56,"VerseNumber":72,"Text":"¿Habéis hecho crecer vosotros el árbol que lo alimenta o somos Nosotros Quienes lo han hecho crecer"},{"SurahNumber":56,"VerseNumber":73,"Text":"Nosotros hemos hecho eso como recuerdo y utilidad para los habitantes del desierto"},{"SurahNumber":56,"VerseNumber":74,"Text":"¡Glorifica, pues, el nombre de tu Señor, el Grandioso"},{"SurahNumber":56,"VerseNumber":75,"Text":"¡Pues no! ¡Juro por el ocaso de las estrellas"},{"SurahNumber":56,"VerseNumber":76,"Text":"Juramento en verdad-si supierais...-solemne"},{"SurahNumber":56,"VerseNumber":77,"Text":"¡Es, en verdad, un Corán noble"},{"SurahNumber":56,"VerseNumber":78,"Text":"contenido en una Escritura escondida"},{"SurahNumber":56,"VerseNumber":79,"Text":"que sólo los purificados tocan"},{"SurahNumber":56,"VerseNumber":80,"Text":"una revelación que procede del Señor del universo"},{"SurahNumber":56,"VerseNumber":81,"Text":"¡Tenéis en poco este discurso"},{"SurahNumber":56,"VerseNumber":82,"Text":"y hacéis de vuestra desmentida vuestro sustento"},{"SurahNumber":56,"VerseNumber":83,"Text":"¿Por qué, pues, cuando se sube a la garganta"},{"SurahNumber":56,"VerseNumber":84,"Text":"viéndolo vosotros"},{"SurahNumber":56,"VerseNumber":85,"Text":"y Nosotros estamos más cerca que vosotros de él, pero no percibís"},{"SurahNumber":56,"VerseNumber":86,"Text":"por qué, pues, si no vais a ser juzgados"},{"SurahNumber":56,"VerseNumber":87,"Text":"y es verdad lo que decís, no la hacéis volver"},{"SurahNumber":56,"VerseNumber":88,"Text":"Si figura entre los allegados"},{"SurahNumber":56,"VerseNumber":89,"Text":"tendrá reposo, plantas aromáticas y jardín de delicia"},{"SurahNumber":56,"VerseNumber":90,"Text":"Si es de los de la derecha"},{"SurahNumber":56,"VerseNumber":91,"Text":"«¡Paz a ti, que eres de los de la derecha!»"},{"SurahNumber":56,"VerseNumber":92,"Text":"Pero, si es de los extraviados desmentidores"},{"SurahNumber":56,"VerseNumber":93,"Text":"será alojado en agua muy caliente"},{"SurahNumber":56,"VerseNumber":94,"Text":"y arderá en fuego de gehena"},{"SurahNumber":56,"VerseNumber":95,"Text":"¡Esto es algo, sí, absolutamente cierto"},{"SurahNumber":56,"VerseNumber":96,"Text":"¡Glorifica, pues, el nombre de tu Señor, el Grandioso"},{"SurahNumber":57,"VerseNumber":1,"Text":"Lo que está en los cielos y en la tierra glorifica a Alá. Él es el Poderoso, el Sabio"},{"SurahNumber":57,"VerseNumber":2,"Text":"Suyo es el dominio de los cielos y de la tierra. Él da la vida y da la muerte. Y es omnipotente"},{"SurahNumber":57,"VerseNumber":3,"Text":"Él es el Principio y el Fin, el Visible y el Escondido. Y es omnisciente"},{"SurahNumber":57,"VerseNumber":4,"Text":"Él es Quien creó los cielos y la tierra en seis días. Luego, se instaló en el Trono. Sabe lo que penetra en la tierra y lo que de ella sale, lo que desciende del cielo y lo que a él asciende. Está con vosotros dondequiera que os encontréis. Alá ve bien lo que hacéis"},{"SurahNumber":57,"VerseNumber":5,"Text":"Suyo es el dominio de los cielos y de la tierra. ¡Y todo será devuelto a Alá"},{"SurahNumber":57,"VerseNumber":6,"Text":"Hace que la noche entre en el día y que el día entre en la noche. Y Él sabe bien lo que encierran los pechos"},{"SurahNumber":57,"VerseNumber":7,"Text":"¡Creed en Alá y en Su Enviado! Dad limosna de los bienes de los que Él os ha hecho últimos poseedores. Aquéllos de vosotros que hayan creído y dado limosna tendrán una gran recompensa"},{"SurahNumber":57,"VerseNumber":8,"Text":"Y ¿por qué no habéis de creer en Alá, siendo así que el Enviado os invita a creer en vuestro Señor y que ha concertado un pacto con vosotros? Si es que sois creyentes"},{"SurahNumber":57,"VerseNumber":9,"Text":"Él es Quien revela a Su siervo signos claros para sacaros de las tinieblas a la luz. En verdad, Alá es manso, misericordioso con vosotros"},{"SurahNumber":57,"VerseNumber":10,"Text":"Y ¿por qué no habéis de gastar por la causa de Alá, siendo así que la herencia de los cielos y de la tierra pertenece a Alá? No seréis todos iguales: unos, que han gastado y combatido antes del Éxito, tendrán una categoría más elevada que otros que han gastado y combatido después de ella. A todos, sin embargo, ha prometido Alá lo mejor. Alá está bien informado de lo que hacéis"},{"SurahNumber":57,"VerseNumber":11,"Text":"A quien haga a Alá un préstamo generoso, Él le devolverá el doble y le recompensará generosamente"},{"SurahNumber":57,"VerseNumber":12,"Text":"El día que veas la luz de los creyentes y de las creyentes correr ante ellos y a su derecha: «¡Buena nueva hoy para vosotros: jardines por cuyos bajos fluyen arroyos, en los que estaréis por toda la eternidad! ¡Ése es el éxito grandioso!»"},{"SurahNumber":57,"VerseNumber":13,"Text":"El día que los hipócritas y las hipócritas digan a los que creyeron: «¡Esperad a que tomemos de vuestra luz!» Se dirá: «¡Retroceded! ¡Buscad una luz!» Entre ellos se levantará una muralla con una puerta. Dentro estará la Misericordia y fuera, enfrente, el Castigo"},{"SurahNumber":57,"VerseNumber":14,"Text":"Les llamarán: «¿No estábamos con vosotros?» Dirán: «¡Claro que sí! Pero os dejasteis seducir, os mantuvisteis a la expectativa, dudasteis. Vuestros anhelos os engañaron hasta que vino la orden de Alá. El Engañador os engañó acerca de Alá"},{"SurahNumber":57,"VerseNumber":15,"Text":"Hoy no se aceptará ningún rescate por parte vuestra ni por parte de los que no creyeron. Vuestra morada será el Fuego, que es vuestro lugar apropiado». ¡Qué mal fin"},{"SurahNumber":57,"VerseNumber":16,"Text":"¿No es hora ya de que se humillen los corazones de los creyentes ante la Amonestación de Alá y ante la Verdad revelada y de que no sean como quienes, habiendo recibido antes la Escritura, dejaron pasar tanto tiempo que se endureció su corazón? Muchos de ellos eran unos perversos"},{"SurahNumber":57,"VerseNumber":17,"Text":"¡Sabed que Alá vivifica la tierra después de muerta. Os hemos explicado las aleyas. Quizás, así, comprendáis"},{"SurahNumber":57,"VerseNumber":18,"Text":"A quienes den limosna, ellos y ellas, haciendo un préstamo generoso a Alá, les devolverá el doble y les recompensará generosamente"},{"SurahNumber":57,"VerseNumber":19,"Text":"Los que crean en Alá y en Sus enviados serán los veraces y los testigos ante su Señor. Recibirán su recompensa y su luz. Pero quienes no crean y desmientan Nuestros signos morarán en el fuego de la gehena"},{"SurahNumber":57,"VerseNumber":20,"Text":"¡Sabed que la vida de acá es juego, distracción y ornato, revalidad en jactancia, afán de más hacienda, de más hijos! Es como un chaparrón: la vegetación resultante alegra a los sembradores, pero luego se marchita y ves que amarillea; luego, se convierte en paja seca. En la otra vida habrá castigo severo o perdón y satisfacción de Alá, mientras que la vida de acá no es más que falaz disfrute"},{"SurahNumber":57,"VerseNumber":21,"Text":"¡Rivalizad en la obtención del perdón de vuestro Señor y de un Jardín tan vasto como el cielo y la tierra, preparado para los que creen en Alá y en Sus enviados! Ese es el favor de Alá, que da a quien Él quiere. Alá es el Dueño del favor in menso"},{"SurahNumber":57,"VerseNumber":22,"Text":"No ocurre ninguna desgracia, ni a la tierra ni a vosotros mismos, que no esté en una Escritura antes de que la ocasionemos. Es cosa fácil para Alá"},{"SurahNumber":57,"VerseNumber":23,"Text":"Para que no desesperéis si no conseguís algo y para que no os regocijéis si lo conseguís. Alá no ama a nadie que sea presumido, jactancioso"},{"SurahNumber":57,"VerseNumber":24,"Text":"a los avaros que ordenan avaricia a los hombres. Pero quien vuelve la espalda..., Alá es Quien Se basta a Sí mismo, el Digno de Alabanza"},{"SurahNumber":57,"VerseNumber":25,"Text":"Ya hemos mandado a nuestros enviados con las pruebas claras. Y hemos hecho descender con ellos la Escritura y la Balanza, para que los hombres observen la equidad. Hemos hecho descender el hierro, que encierra una gran fuerza y ventajas para los hombres. A fin de que Alá sepa quiénes les auxilian en secreto, a Él y a Sus enviados. Alá es fuerte poderoso"},{"SurahNumber":57,"VerseNumber":26,"Text":"Ya hemos enviado a Noé y a Abraham y confiado a su descendencia el profetismo y la Escritura. Entre sus descendientes los hubo bien dirigidos, pero muchos de ellos fueron unos perversos"},{"SurahNumber":57,"VerseNumber":27,"Text":"Tras ellos, mandamos a Nuestros otros enviados, así como Jesús, hijo de María, a quien dimos el Evangelio. Pusimos en los corazones de quienes le siguieron mansedumbre, misericordia y monacato. Este último fue instaurado por ellos -no se lo prescribimos Nosotros- sólo por deseo de satisfacer a Alá, pero no lo observaron como debían. Remuneramos a quienes de ellos creyeron, pero muchos de ellos fueron unos perversos"},{"SurahNumber":57,"VerseNumber":28,"Text":"¡Creyentes! ¡Temed a Alá y creed en Su Enviado! Os dará, así, participación doble en Su misericordia, os pondrá una Luz que ilumine vuestra marcha y os perdonará. Alá es indulgente, misericordioso"},{"SurahNumber":57,"VerseNumber":29,"Text":"¡Que la gente de la Escritura sepa que no puede disponer nada del favor de Alá, que el favor está en la mano de Alá, que da a quien Él quiere! ¡Alá es el Dueño del favor inmenso"}]}