{"Type":"page","Number":514,"DefaultUrl":"048.mp3","TotalDurationMs":null,"Segments":[{"I":0,"S":48,"V":24,"Url":"048.mp3","StartMs":311383,"EndMs":323765,"DurationMs":12382},{"I":1,"S":48,"V":25,"Url":"048.mp3","StartMs":323765,"EndMs":361257,"DurationMs":37492},{"I":2,"S":48,"V":26,"Url":"048.mp3","StartMs":361257,"EndMs":380793,"DurationMs":19536},{"I":3,"S":48,"V":27,"Url":"048.mp3","StartMs":380793,"EndMs":400958,"DurationMs":20165},{"I":4,"S":48,"V":28,"Url":"048.mp3","StartMs":400958,"EndMs":410995,"DurationMs":10037}]}