{"Id":419,"LanguageCodes":["tr","tur"],"Name":"tur-muhammetabay","Author":"Muhammet Abay","Language":"Turkish","Description":"Turkish","Direction":"ltr","Source":"http://tanzil.net","Translations":[{"SurahNumber":42,"VerseNumber":32,"Text":"vemin âyâtihi-lcevâri fi-lbaḥri kel'a`lâm"},{"SurahNumber":42,"VerseNumber":33,"Text":"iy yeşe' yüskini-rrîḥa feyażlelne ravâkide `alâ żahrih. inne fî ẕâlike leâyâtil likülli ṣabbârin şekûr"},{"SurahNumber":42,"VerseNumber":34,"Text":"ev yûbiḳhünne bimâ kesebû veya`fü `an keŝîr"},{"SurahNumber":42,"VerseNumber":35,"Text":"veya`leme-lleẕîne yücâdilûne fî âyâtinâ. mâ lehüm mim meḥîṣ"},{"SurahNumber":42,"VerseNumber":36,"Text":"femâ ûtîtüm min şey'in femetâ`u-lḥayâti-ddünyâ. vemâ `inde-llâhi ḫayruv veebḳâ lilleẕîne âmenû ve`alâ rabbihim yetevekkelûn"},{"SurahNumber":42,"VerseNumber":37,"Text":"velleẕîne yectenibûne kebâira-l'iŝmi velfevâḥişe veiẕâ mâ gaḍibû hüm yagfirûn"},{"SurahNumber":42,"VerseNumber":38,"Text":"velleẕîne-stecâbû lirabbihim veeḳâmu-ṣṣalâh. veemruhüm şûrâ beynehüm. vemimmâ razaḳnâhüm yünfiḳûn"},{"SurahNumber":42,"VerseNumber":39,"Text":"velleẕîne iẕâ eṣâbehümü-lbagyü hüm yenteṣirûn"},{"SurahNumber":42,"VerseNumber":40,"Text":"vecezâü seyyietin seyyietüm miŝlühâ. femen `afâ veaṣleḥa feecruhû `ale-llâh. innehû lâ yüḥibbu-żżâlimîn"},{"SurahNumber":42,"VerseNumber":41,"Text":"velemeni-nteṣara ba`de żulmihî feülâike mâ `aleyhim min sebîl"},{"SurahNumber":42,"VerseNumber":42,"Text":"inneme-ssebîlü `ale-lleẕîne yażlimûne-nnâse veyebgûne fi-l'arḍi bigayri-lḥaḳḳ. ülâike lehüm `aẕâbün elîm"},{"SurahNumber":42,"VerseNumber":43,"Text":"velemen ṣabera vegafera inne ẕâlike lemin `azmi-l'ümûr"},{"SurahNumber":42,"VerseNumber":44,"Text":"vemey yuḍlili-llâhü femâ lehû miv veliyyim mim ba`dih. vetera-żżâlimîne lemmâ raevu-l`aẕâbe yeḳûlûne hel ilâ meraddim min sebîl"}]}