[{"Id":"3C6BB6A6FA45933A2C425FC2382958FCBB257862C203A8F6EF400CDFE303052D","Category":2,"CategoryType":2,"ReviewSourceValue":null,"ReviewDestinationValue":null,"Question":{"Type":"text","Value":"to fear","TextDirection":"ltr","AudioFileName":null,"Choices":["يُرْهِقَ","يُضَآرَّ","سَحَرُ","ٱهْجُرْ","سَرِّحُ","زَالَ","زُلْزِلُ","يَشَّقَّقُ","يَسْـَٔمُ","تُسْقِطَ","يَرْهَبُ"]},"Answer":{"Type":"text","Value":"يَرْهَبُ","TextDirection":"rtl"},"AudioFileName":null,"ExtendedProperties":[]},{"Id":"3C6BB6A6FA45933A2C425FC2382958FCBB257862C203A8F6EF400CDFE303052D","Category":2,"CategoryType":4,"ReviewSourceValue":null,"ReviewDestinationValue":null,"Question":{"Type":"text","Value":"يَرْهَبُ","TextDirection":"rtl","AudioFileName":null,"Choices":["to release","to shake","to pour","to cover","to tire","to swear","to turn","to return","to repel","to cease","to fear"]},"Answer":{"Type":"text","Value":"to fear","TextDirection":"ltr"},"AudioFileName":null,"ExtendedProperties":[]},{"Id":"32E0560DDDF423C1E06E99AFB3EC13273C646E8B79F4CEF711828E957A184202","Category":2,"CategoryType":2,"ReviewSourceValue":null,"ReviewDestinationValue":null,"Question":{"Type":"text","Value":"to be hard on, to overburden, to cover","TextDirection":"ltr","AudioFileName":null,"Choices":["يَرْهَبُ","يَشَّقَّقُ","يُسْجَنَ","زَهَقَ","سَرِّحُ","يَسْـَٔمُ","زَالَ","سُقِطَ","رَاغَ","تُسْقِطَ","يُرْهِقَ"]},"Answer":{"Type":"text","Value":"يُرْهِقَ","TextDirection":"rtl"},"AudioFileName":null,"ExtendedProperties":[]},{"Id":"32E0560DDDF423C1E06E99AFB3EC13273C646E8B79F4CEF711828E957A184202","Category":2,"CategoryType":4,"ReviewSourceValue":null,"ReviewDestinationValue":null,"Question":{"Type":"text","Value":"يُرْهِقَ","TextDirection":"rtl","AudioFileName":null,"Choices":["to suffer, to be harmed","to approach, to go near","to depart, to perish","to turn, to alternate","to bewitch, to delude","to cause toll, to cause to fall","to be patient, to be steadfast","to resolve, to decide, to determine","to eat, to taste, to feed","to turn","to be hard on, to overburden, to cover"]},"Answer":{"Type":"text","Value":"to be hard on, to overburden, to cover","TextDirection":"ltr"},"AudioFileName":null,"ExtendedProperties":[]},{"Id":"FE46A16C63083F34FBC54FA9838AABFF3660A20635E79479C590352372955D4D","Category":2,"CategoryType":2,"ReviewSourceValue":null,"ReviewDestinationValue":null,"Question":{"Type":"text","Value":"to turn","TextDirection":"ltr","AudioFileName":null,"Choices":["زَالَ","حَاقَ","زَهَقَ","شَرَحَ","بَعَثَ","رَّضِىَ","غَدَ","سُقِطَ","يَجُرُّ","دَامُ","رَاغَ"]},"Answer":{"Type":"text","Value":"رَاغَ","TextDirection":"rtl"},"AudioFileName":null,"ExtendedProperties":[]},{"Id":"FE46A16C63083F34FBC54FA9838AABFF3660A20635E79479C590352372955D4D","Category":2,"CategoryType":4,"ReviewSourceValue":null,"ReviewDestinationValue":null,"Question":{"Type":"text","Value":"رَاغَ","TextDirection":"rtl","AudioFileName":null,"Choices":["to tire","to release","to shake","to fear","to appoint","to replace","to split","to cease","to pick","to hoard","to turn"]},"Answer":{"Type":"text","Value":"to turn","TextDirection":"ltr"},"AudioFileName":null,"ExtendedProperties":[]},{"Id":"3F9E34048E05E2D8EA4CF47AF3821BADE5E81BF30996F8328A6A3FDDDF94F530","Category":2,"CategoryType":2,"ReviewSourceValue":null,"ReviewDestinationValue":null,"Question":{"Type":"text","Value":"to shake","TextDirection":"ltr","AudioFileName":null,"Choices":["زَالَ","سَحَرُ","سَرِّحُ","يُرْهِقَ","ٱصْطَبِرْ","يُبْلِسُ","زَهَقَ","يَسْـَٔمُ","يَرْهَبُ","يُضَآرَّ","زُلْزِلُ"]},"Answer":{"Type":"text","Value":"زُلْزِلُ","TextDirection":"rtl"},"AudioFileName":null,"ExtendedProperties":[]},{"Id":"3F9E34048E05E2D8EA4CF47AF3821BADE5E81BF30996F8328A6A3FDDDF94F530","Category":2,"CategoryType":4,"ReviewSourceValue":null,"ReviewDestinationValue":null,"Question":{"Type":"text","Value":"زُلْزِلُ","TextDirection":"rtl","AudioFileName":null,"Choices":["to cease","to split","to release","to tire","to turn","to fear","to weigh","to give","to imprison","to remove","to shake"]},"Answer":{"Type":"text","Value":"to shake","TextDirection":"ltr"},"AudioFileName":null,"ExtendedProperties":[]},{"Id":"EF77FC7B144E9E30EE7BE8569508AB5879E984F0AC19ED509C87923D960284FE","Category":2,"CategoryType":2,"ReviewSourceValue":null,"ReviewDestinationValue":null,"Question":{"Type":"text","Value":"to depart, to perish","TextDirection":"ltr","AudioFileName":null,"Choices":["يُرْهِقَ","زَالَ","سُقِطَ","تُسْقِطَ","رَاغَ","ٱصْطَبِرْ","يُسْجَنَ","يَسْـَٔمُ","كَفَرَ","يَرْهَبُ","زَهَقَ"]},"Answer":{"Type":"text","Value":"زَهَقَ","TextDirection":"rtl"},"AudioFileName":null,"ExtendedProperties":[]},{"Id":"EF77FC7B144E9E30EE7BE8569508AB5879E984F0AC19ED509C87923D960284FE","Category":2,"CategoryType":4,"ReviewSourceValue":null,"ReviewDestinationValue":null,"Question":{"Type":"text","Value":"زَهَقَ","TextDirection":"rtl","AudioFileName":null,"Choices":["to be patient, to be steadfast","to release","to bewitch, to delude","to imprison","to restrain, to besiege","to suffer, to be harmed","to send forth","to err, to make mistake","to mislead, to lead astray","to turn away, to depart","to depart, to perish"]},"Answer":{"Type":"text","Value":"to depart, to perish","TextDirection":"ltr"},"AudioFileName":null,"ExtendedProperties":[]},{"Id":"85A5121118660963540BB1AB63E994B8D6DC5150A87E8EAE5DF094BF6FF47A37","Category":2,"CategoryType":2,"ReviewSourceValue":null,"ReviewDestinationValue":null,"Question":{"Type":"text","Value":"to cease","TextDirection":"ltr","AudioFileName":null,"Choices":["رَاغَ","زَهَقَ","سُقِطَ","قَدَّمَ","جَلَّىٰ","بَٰعِدْ","سَحَرُ","سَرِّحُ","أَنطَقَ","نَـَٔا","زَالَ"]},"Answer":{"Type":"text","Value":"زَالَ","TextDirection":"rtl"},"AudioFileName":null,"ExtendedProperties":[]},{"Id":"85A5121118660963540BB1AB63E994B8D6DC5150A87E8EAE5DF094BF6FF47A37","Category":2,"CategoryType":4,"ReviewSourceValue":null,"ReviewDestinationValue":null,"Question":{"Type":"text","Value":"زَالَ","TextDirection":"rtl","AudioFileName":null,"Choices":["to escape","to shake","to release","to choose","to tire","to split","to fear","to imprison","to forgive","to exceed","to cease"]},"Answer":{"Type":"text","Value":"to cease","TextDirection":"ltr"},"AudioFileName":null,"ExtendedProperties":[]},{"Id":"46596C916AA7BF7951E91E69621B97DCB2AF2131ACD159EF3F98BF764B0522DE","Category":2,"CategoryType":2,"ReviewSourceValue":null,"ReviewDestinationValue":null,"Question":{"Type":"text","Value":"to tire","TextDirection":"ltr","AudioFileName":null,"Choices":["يُسْجَنَ","سَرِّحُ","سُقِطَ","يُضَآرَّ","يُرْهِقَ","يَتَمَآسَّ","يَغِيظُ","يَرْهَبُ","يَفْسَحِ","ٱؤْتُمِنَ","يَسْـَٔمُ"]},"Answer":{"Type":"text","Value":"يَسْـَٔمُ","TextDirection":"rtl"},"AudioFileName":null,"ExtendedProperties":[]},{"Id":"46596C916AA7BF7951E91E69621B97DCB2AF2131ACD159EF3F98BF764B0522DE","Category":2,"CategoryType":4,"ReviewSourceValue":null,"ReviewDestinationValue":null,"Question":{"Type":"text","Value":"يَسْـَٔمُ","TextDirection":"rtl","AudioFileName":null,"Choices":["to release","to fear","to turn","to shake","to cover","to cease","to sit","to enjoin","to appoint","to learn","to tire"]},"Answer":{"Type":"text","Value":"to tire","TextDirection":"ltr"},"AudioFileName":null,"ExtendedProperties":[]},{"Id":"77F0EDF102216F6C93A8CAD5994999E5CA9404D9656455761E58CBC01B3F488C","Category":2,"CategoryType":2,"ReviewSourceValue":null,"ReviewDestinationValue":null,"Question":{"Type":"text","Value":"to imprison","TextDirection":"ltr","AudioFileName":null,"Choices":["يُرْهِقَ","تُسْقِطَ","سُقِطَ","يَسْـَٔمُ","يَجْهَلُ","زُلْزِلُ","يُضَآرَّ","يَرْهَبُ","أَمِنَ","أَبْرَحَ","يُسْجَنَ"]},"Answer":{"Type":"text","Value":"يُسْجَنَ","TextDirection":"rtl"},"AudioFileName":null,"ExtendedProperties":[]},{"Id":"77F0EDF102216F6C93A8CAD5994999E5CA9404D9656455761E58CBC01B3F488C","Category":2,"CategoryType":4,"ReviewSourceValue":null,"ReviewDestinationValue":null,"Question":{"Type":"text","Value":"يُسْجَنَ","TextDirection":"rtl","AudioFileName":null,"Choices":["to persist","to appoint","to split","to turn","to disdain","to cease","to tire","to release","to pour","to hasten","to imprison"]},"Answer":{"Type":"text","Value":"to imprison","TextDirection":"ltr"},"AudioFileName":null,"ExtendedProperties":[]},{"Id":"096034AE6F5EFB0F8F446636F6AF13CC5F96C38586BC5F805085ADE67C8E6BB3","Category":2,"CategoryType":2,"ReviewSourceValue":null,"ReviewDestinationValue":null,"Question":{"Type":"text","Value":"to bewitch, to delude","TextDirection":"ltr","AudioFileName":null,"Choices":["سَرِّحُ","زُلْزِلُ","يُرَآءُ","رَاغَ","يَسْـَٔمُ","ٱصْطَبِرْ","سُقِطَ","تُسْقِطَ","زَالَ","يُرْهِقَ","سَحَرُ"]},"Answer":{"Type":"text","Value":"سَحَرُ","TextDirection":"rtl"},"AudioFileName":null,"ExtendedProperties":[]},{"Id":"096034AE6F5EFB0F8F446636F6AF13CC5F96C38586BC5F805085ADE67C8E6BB3","Category":2,"CategoryType":4,"ReviewSourceValue":null,"ReviewDestinationValue":null,"Question":{"Type":"text","Value":"سَحَرُ","TextDirection":"rtl","AudioFileName":null,"Choices":["to suffer, to be harmed","to descend, to be lawful","to cause toll, to cause to fall","to walk, to circumambulate","to pass away, to die","to stir, to move","to be patient, to be steadfast","to depart, to perish","to hope, to desire","to fall, to regret","to bewitch, to delude"]},"Answer":{"Type":"text","Value":"to bewitch, to delude","TextDirection":"ltr"},"AudioFileName":null,"ExtendedProperties":[]},{"Id":"000D0BCC88CDD01BDC3FB80729F2CCA6FD9A7DC87B60EED7A14B9CA180978D1D","Category":2,"CategoryType":2,"ReviewSourceValue":null,"ReviewDestinationValue":null,"Question":{"Type":"text","Value":"to release","TextDirection":"ltr","AudioFileName":null,"Choices":["سَحَرُ","يَسْـَٔمُ","ذُكِّرَ","سُقِطَ","زَالَ","زُلْزِلُ","ٱصْطَبِرْ","يُنزَفُ","زَهَقَ","يَمْحَقُ","سَرِّحُ"]},"Answer":{"Type":"text","Value":"سَرِّحُ","TextDirection":"rtl"},"AudioFileName":null,"ExtendedProperties":[]},{"Id":"000D0BCC88CDD01BDC3FB80729F2CCA6FD9A7DC87B60EED7A14B9CA180978D1D","Category":2,"CategoryType":4,"ReviewSourceValue":null,"ReviewDestinationValue":null,"Question":{"Type":"text","Value":"سَرِّحُ","TextDirection":"rtl","AudioFileName":null,"Choices":["to shake","to fear","to spare","to prostrate","to cease","to steal","to blame","to split","to tire","to not be","to release"]},"Answer":{"Type":"text","Value":"to release","TextDirection":"ltr"},"AudioFileName":null,"ExtendedProperties":[]},{"Id":"021E6A0971F155D2DEE4B7C1FAED3FB6DF8D7CC41FB541E66D27BAC1C6199197","Category":2,"CategoryType":2,"ReviewSourceValue":null,"ReviewDestinationValue":null,"Question":{"Type":"text","Value":"to fall, to regret","TextDirection":"ltr","AudioFileName":null,"Choices":["تُسْقِطَ","سَرِّحُ","يُرْهِقَ","سَحَرُ","يُسْجَنَ","ٱصْطَبِرْ","زَهَقَ","يَسْـَٔمُ","رَاغَ","يَرْهَبُ","سُقِطَ"]},"Answer":{"Type":"text","Value":"سُقِطَ","TextDirection":"rtl"},"AudioFileName":null,"ExtendedProperties":[]},{"Id":"021E6A0971F155D2DEE4B7C1FAED3FB6DF8D7CC41FB541E66D27BAC1C6199197","Category":2,"CategoryType":4,"ReviewSourceValue":null,"ReviewDestinationValue":null,"Question":{"Type":"text","Value":"سُقِطَ","TextDirection":"rtl","AudioFileName":null,"Choices":["to release","to swim, to float","to be arrogant","to fear, to be afraid","to suffer, to be harmed","to bewitch, to delude","to oppose, to differ","to strengthen","to appoint","to seek shelter","to fall, to regret"]},"Answer":{"Type":"text","Value":"to fall, to regret","TextDirection":"ltr"},"AudioFileName":null,"ExtendedProperties":[]},{"Id":"317E8A04FA943234F945D0062274758CD48B075F12FB5689D08E5BEE7785CF32","Category":2,"CategoryType":2,"ReviewSourceValue":null,"ReviewDestinationValue":null,"Question":{"Type":"text","Value":"to cause toll, to cause to fall","TextDirection":"ltr","AudioFileName":null,"Choices":["طُمِسَتْ","سُقِطَ","سَرِّحُ","سَحَرُ","يَسْـَٔمُ","يَسْتَفْتُ","يُسْجَنَ","رَاغَ","ٱصْطَبِرْ","زَهَقَ","تُسْقِطَ"]},"Answer":{"Type":"text","Value":"تُسْقِطَ","TextDirection":"rtl"},"AudioFileName":null,"ExtendedProperties":[]},{"Id":"317E8A04FA943234F945D0062274758CD48B075F12FB5689D08E5BEE7785CF32","Category":2,"CategoryType":4,"ReviewSourceValue":null,"ReviewDestinationValue":null,"Question":{"Type":"text","Value":"تُسْقِطَ","TextDirection":"rtl","AudioFileName":null,"Choices":["to be patient, to be steadfast","to depart, to perish","to be hard on, to overburden, to cover","to fall, to regret","to differentiate, to make distinction","to suffer, to be harmed","to test, to examine","to bewitch, to delude","to announce, to proclaim","to absolve, to clear","to cause toll, to cause to fall"]},"Answer":{"Type":"text","Value":"to cause toll, to cause to fall","TextDirection":"ltr"},"AudioFileName":null,"ExtendedProperties":[]},{"Id":"52781626FA36A5D24BD9F4844C345882E0614CC98E3EAC3A46812954D0F2360C","Category":2,"CategoryType":2,"ReviewSourceValue":null,"ReviewDestinationValue":null,"Question":{"Type":"text","Value":"to split","TextDirection":"ltr","AudioFileName":null,"Choices":["يُرْهِقَ","زُلْزِلُ","يُضَآرَّ","يَتَخَيَّرُ","زَهَقَ","سُقِطَ","يَرْهَبُ","يُحَآدُّ","زَالَ","يُسْجَنَ","يَشَّقَّقُ"]},"Answer":{"Type":"text","Value":"يَشَّقَّقُ","TextDirection":"rtl"},"AudioFileName":null,"ExtendedProperties":[]},{"Id":"52781626FA36A5D24BD9F4844C345882E0614CC98E3EAC3A46812954D0F2360C","Category":2,"CategoryType":4,"ReviewSourceValue":null,"ReviewDestinationValue":null,"Question":{"Type":"text","Value":"يَشَّقَّقُ","TextDirection":"rtl","AudioFileName":null,"Choices":["to imprison","to release","to miss","to shake","to turn","to commit","to cease","to tire","to return","to fear","to split"]},"Answer":{"Type":"text","Value":"to split","TextDirection":"ltr"},"AudioFileName":null,"ExtendedProperties":[]},{"Id":"D18D3E61261DF8A1A0241BAC2DBAA361F6211BCB6573B295F0096DB51248EB7A","Category":2,"CategoryType":2,"ReviewSourceValue":null,"ReviewDestinationValue":null,"Question":{"Type":"text","Value":"to be patient, to be steadfast","TextDirection":"ltr","AudioFileName":null,"Choices":["تَرَبَّصْ","تُسْقِطَ","سَرِّحُ","يَرْهَبُ","زَهَقَ","رَاغَ","سُقِطَ","يَسْـَٔمُ","طَفِقَ","تَنَزَّلَتْ","ٱصْطَبِرْ"]},"Answer":{"Type":"text","Value":"ٱصْطَبِرْ","TextDirection":"rtl"},"AudioFileName":null,"ExtendedProperties":[]},{"Id":"D18D3E61261DF8A1A0241BAC2DBAA361F6211BCB6573B295F0096DB51248EB7A","Category":2,"CategoryType":4,"ReviewSourceValue":null,"ReviewDestinationValue":null,"Question":{"Type":"text","Value":"ٱصْطَبِرْ","TextDirection":"rtl","AudioFileName":null,"Choices":["to depart, to perish","to be hard on, to overburden, to cover","to bewitch, to delude","to encompass, to extend","to suffer, to be harmed","to be many, to be frequent","to cause toll, to cause to fall","to distance, to become remote, to keep away","to entice, to suggest","to leave, to cease","to be patient, to be steadfast"]},"Answer":{"Type":"text","Value":"to be patient, to be steadfast","TextDirection":"ltr"},"AudioFileName":null,"ExtendedProperties":[]},{"Id":"E2EAA3A020266543D7177776AFECFF6596B40838979BD9A5EF18B7E990864960","Category":2,"CategoryType":2,"ReviewSourceValue":null,"ReviewDestinationValue":null,"Question":{"Type":"text","Value":"to suffer, to be harmed","TextDirection":"ltr","AudioFileName":null,"Choices":["يَجُرُّ","يَشَّقَّقُ","سَرِّحُ","سَحَرُ","يَرْهَبُ","يُرْهِقَ","زُلْزِلُ","زَالَ","رَاغَ","سُقِطَ","يُضَآرَّ"]},"Answer":{"Type":"text","Value":"يُضَآرَّ","TextDirection":"rtl"},"AudioFileName":null,"ExtendedProperties":[]},{"Id":"E2EAA3A020266543D7177776AFECFF6596B40838979BD9A5EF18B7E990864960","Category":2,"CategoryType":4,"ReviewSourceValue":null,"ReviewDestinationValue":null,"Question":{"Type":"text","Value":"يُضَآرَّ","TextDirection":"rtl","AudioFileName":null,"Choices":["to be patient, to be steadfast","to cause toll, to cause to fall","to fall, to regret","to depart, to perish","to bewitch, to delude","to support, to back","to overtake, to grasp","to be exalted, to be high","to withhold, to withdraw, to close","to perceive, to realize","to suffer, to be harmed"]},"Answer":{"Type":"text","Value":"to suffer, to be harmed","TextDirection":"ltr"},"AudioFileName":null,"ExtendedProperties":[]}]