{"Id":84,"LanguageCodes":["da","dan"],"Name":"dan-hadiabdollahian","Author":"Hadi Abdollahian","Language":"Danish","Description":"Danish","Direction":"ltr","Source":"https://www.alqurantranslation.com/ , Contact:+989354664487","Translations":[{"SurahNumber":78,"VerseNumber":31,"Text":"righteous trænge belønning"},{"SurahNumber":78,"VerseNumber":32,"Text":"Frugthaver drue"},{"SurahNumber":78,"VerseNumber":33,"Text":"Storslåede ægtefæller"},{"SurahNumber":78,"VerseNumber":34,"Text":"Dejlige drinks"},{"SurahNumber":78,"VerseNumber":35,"Text":"De aldrig høre det nogen nonsens løgne"},{"SurahNumber":78,"VerseNumber":36,"Text":"Belønning fra Deres Lord gavmilde recompense"},{"SurahNumber":78,"VerseNumber":37,"Text":"Lord af himlene jorden alt dem. Mest Gracious. Ingen abrogate Hans bestemmelser"},{"SurahNumber":78,"VerseNumber":38,"Text":"Dagen komme hvornår Ånden englene stå række! Ingen tale de permitted ved mest Gracious de utter kun hvad er omgående"},{"SurahNumber":78,"VerseNumber":39,"Text":"Such er uundgåelige dagen. Whoever viljer lade ham tage ly hans Lord"},{"SurahNumber":78,"VerseNumber":40,"Text":"Vi tilstrækkeligt advarer jer forestående gengældelse. Den er dagen hvornår enhver ransage hvad hans hænder sender væk tvivleren sie Ohio Jeg ønske jeg var støv"}]}