{"Type":"page","Number":56,"DefaultUrl":"003.mp3","TotalDurationMs":null,"Segments":[{"I":0,"S":3,"V":46,"Url":"003.mp3","StartMs":811248,"EndMs":818000,"DurationMs":6752},{"I":1,"S":3,"V":47,"Url":"003.mp3","StartMs":818000,"EndMs":840423,"DurationMs":22423},{"I":2,"S":3,"V":48,"Url":"003.mp3","StartMs":840423,"EndMs":847127,"DurationMs":6704},{"I":3,"S":3,"V":49,"Url":"003.mp3","StartMs":847127,"EndMs":886319,"DurationMs":39192},{"I":4,"S":3,"V":50,"Url":"003.mp3","StartMs":886319,"EndMs":901983,"DurationMs":15664},{"I":5,"S":3,"V":51,"Url":"003.mp3","StartMs":901983,"EndMs":914959,"DurationMs":12976},{"I":6,"S":3,"V":52,"Url":"003.mp3","StartMs":914959,"EndMs":934122,"DurationMs":19163}]}