{"Type":"maqra","Number":40,"DefaultUrl":"https://download.quranicaudio.com/qdc/abdul_baset/murattal/1.mp3","TotalDurationMs":null,"Segments":[{"I":0,"S":4,"V":135,"Url":"https://download.quranicaudio.com/qdc/abdul_baset/murattal/4.mp3","StartMs":4061990,"EndMs":4115130,"DurationMs":-53140},{"I":1,"S":4,"V":136,"Url":"https://download.quranicaudio.com/qdc/abdul_baset/murattal/4.mp3","StartMs":4115130,"EndMs":4158410,"DurationMs":-43280},{"I":2,"S":4,"V":137,"Url":"https://download.quranicaudio.com/qdc/abdul_baset/murattal/4.mp3","StartMs":4158410,"EndMs":4182060,"DurationMs":-23650},{"I":3,"S":4,"V":138,"Url":"https://download.quranicaudio.com/qdc/abdul_baset/murattal/4.mp3","StartMs":4182060,"EndMs":4191440,"DurationMs":-9380},{"I":4,"S":4,"V":139,"Url":"https://download.quranicaudio.com/qdc/abdul_baset/murattal/4.mp3","StartMs":4191440,"EndMs":4215560,"DurationMs":-24120},{"I":5,"S":4,"V":140,"Url":"https://download.quranicaudio.com/qdc/abdul_baset/murattal/4.mp3","StartMs":4215560,"EndMs":4254670,"DurationMs":-39110},{"I":6,"S":4,"V":141,"Url":"https://download.quranicaudio.com/qdc/abdul_baset/murattal/4.mp3","StartMs":4254670,"EndMs":4304230,"DurationMs":-49560},{"I":7,"S":4,"V":142,"Url":"https://download.quranicaudio.com/qdc/abdul_baset/murattal/4.mp3","StartMs":4304230,"EndMs":4329230,"DurationMs":-25000},{"I":8,"S":4,"V":143,"Url":"https://download.quranicaudio.com/qdc/abdul_baset/murattal/4.mp3","StartMs":4329230,"EndMs":4357760,"DurationMs":-28530},{"I":9,"S":4,"V":144,"Url":"https://download.quranicaudio.com/qdc/abdul_baset/murattal/4.mp3","StartMs":4357760,"EndMs":4385590,"DurationMs":-27830},{"I":10,"S":4,"V":145,"Url":"https://download.quranicaudio.com/qdc/abdul_baset/murattal/4.mp3","StartMs":4385590,"EndMs":4400280,"DurationMs":-14690},{"I":11,"S":4,"V":146,"Url":"https://download.quranicaudio.com/qdc/abdul_baset/murattal/4.mp3","StartMs":4400280,"EndMs":4425470,"DurationMs":-25190},{"I":12,"S":4,"V":147,"Url":"https://download.quranicaudio.com/qdc/abdul_baset/murattal/4.mp3","StartMs":4425470,"EndMs":4442450,"DurationMs":-16980}]}