{"Type":"ruku","Number":420,"DefaultUrl":"https://static.gtaf.org/v1/quran/audio-url/abdullah_matroud/042.mp3","TotalDurationMs":null,"Segments":[{"I":0,"S":42,"V":10,"Url":"https://static.gtaf.org/v1/quran/audio-url/abdullah_matroud/042.mp3","StartMs":139152,"EndMs":156442,"DurationMs":17290},{"I":1,"S":42,"V":11,"Url":"https://static.gtaf.org/v1/quran/audio-url/abdullah_matroud/042.mp3","StartMs":156442,"EndMs":179811,"DurationMs":23369},{"I":2,"S":42,"V":12,"Url":"https://static.gtaf.org/v1/quran/audio-url/abdullah_matroud/042.mp3","StartMs":179811,"EndMs":196686,"DurationMs":16875},{"I":3,"S":42,"V":13,"Url":"https://static.gtaf.org/v1/quran/audio-url/abdullah_matroud/042.mp3","StartMs":196686,"EndMs":238799,"DurationMs":42113},{"I":4,"S":42,"V":14,"Url":"https://static.gtaf.org/v1/quran/audio-url/abdullah_matroud/042.mp3","StartMs":238799,"EndMs":270009,"DurationMs":31210},{"I":5,"S":42,"V":15,"Url":"https://static.gtaf.org/v1/quran/audio-url/abdullah_matroud/042.mp3","StartMs":270009,"EndMs":312657,"DurationMs":42648},{"I":6,"S":42,"V":16,"Url":"https://static.gtaf.org/v1/quran/audio-url/abdullah_matroud/042.mp3","StartMs":312657,"EndMs":333509,"DurationMs":20852},{"I":7,"S":42,"V":17,"Url":"https://static.gtaf.org/v1/quran/audio-url/abdullah_matroud/042.mp3","StartMs":333509,"EndMs":347188,"DurationMs":13679},{"I":8,"S":42,"V":18,"Url":"https://static.gtaf.org/v1/quran/audio-url/abdullah_matroud/042.mp3","StartMs":347188,"EndMs":372519,"DurationMs":25331},{"I":9,"S":42,"V":19,"Url":"https://static.gtaf.org/v1/quran/audio-url/abdullah_matroud/042.mp3","StartMs":372519,"EndMs":383805,"DurationMs":11286}]}