{"Type":"page","Number":70,"DefaultUrl":"https://static.gtaf.org/v1/quran/audio-url/hady_toure/003.mp3","TotalDurationMs":null,"Segments":[{"I":0,"S":3,"V":154,"Url":"https://static.gtaf.org/v1/quran/audio-url/hady_toure/003.mp3","StartMs":4284272,"EndMs":4382731,"DurationMs":98459},{"I":1,"S":3,"V":155,"Url":"https://static.gtaf.org/v1/quran/audio-url/hady_toure/003.mp3","StartMs":4382731,"EndMs":4409598,"DurationMs":26867},{"I":2,"S":3,"V":156,"Url":"https://static.gtaf.org/v1/quran/audio-url/hady_toure/003.mp3","StartMs":4409598,"EndMs":4469137,"DurationMs":59539},{"I":3,"S":3,"V":157,"Url":"https://static.gtaf.org/v1/quran/audio-url/hady_toure/003.mp3","StartMs":4469137,"EndMs":4487576,"DurationMs":18439}]}