{"Type":"ruku","Number":456,"DefaultUrl":"https://download.quranicaudio.com/quran/ahmed_ibn_3ali_al-3ajamy/051.mp3","TotalDurationMs":null,"Segments":[{"I":0,"S":51,"V":24,"Url":"https://download.quranicaudio.com/quran/ahmed_ibn_3ali_al-3ajamy/051.mp3","StartMs":123296,"EndMs":128385,"DurationMs":5089},{"I":1,"S":51,"V":25,"Url":"https://download.quranicaudio.com/quran/ahmed_ibn_3ali_al-3ajamy/051.mp3","StartMs":128385,"EndMs":137022,"DurationMs":8637},{"I":2,"S":51,"V":26,"Url":"https://download.quranicaudio.com/quran/ahmed_ibn_3ali_al-3ajamy/051.mp3","StartMs":137022,"EndMs":144171,"DurationMs":7149},{"I":3,"S":51,"V":27,"Url":"https://download.quranicaudio.com/quran/ahmed_ibn_3ali_al-3ajamy/051.mp3","StartMs":144171,"EndMs":149385,"DurationMs":5214},{"I":4,"S":51,"V":28,"Url":"https://download.quranicaudio.com/quran/ahmed_ibn_3ali_al-3ajamy/051.mp3","StartMs":149385,"EndMs":157548,"DurationMs":8163},{"I":5,"S":51,"V":29,"Url":"https://download.quranicaudio.com/quran/ahmed_ibn_3ali_al-3ajamy/051.mp3","StartMs":157548,"EndMs":167459,"DurationMs":9911},{"I":6,"S":51,"V":30,"Url":"https://download.quranicaudio.com/quran/ahmed_ibn_3ali_al-3ajamy/051.mp3","StartMs":167459,"EndMs":174359,"DurationMs":6900},{"I":7,"S":51,"V":31,"Url":"https://download.quranicaudio.com/quran/ahmed_ibn_3ali_al-3ajamy/051.mp3","StartMs":174359,"EndMs":179171,"DurationMs":4812},{"I":8,"S":51,"V":32,"Url":"https://download.quranicaudio.com/quran/ahmed_ibn_3ali_al-3ajamy/051.mp3","StartMs":179171,"EndMs":186297,"DurationMs":7126},{"I":9,"S":51,"V":33,"Url":"https://download.quranicaudio.com/quran/ahmed_ibn_3ali_al-3ajamy/051.mp3","StartMs":186297,"EndMs":191898,"DurationMs":5601},{"I":10,"S":51,"V":34,"Url":"https://download.quranicaudio.com/quran/ahmed_ibn_3ali_al-3ajamy/051.mp3","StartMs":191898,"EndMs":196960,"DurationMs":5062},{"I":11,"S":51,"V":35,"Url":"https://download.quranicaudio.com/quran/ahmed_ibn_3ali_al-3ajamy/051.mp3","StartMs":196960,"EndMs":202332,"DurationMs":5372},{"I":12,"S":51,"V":36,"Url":"https://download.quranicaudio.com/quran/ahmed_ibn_3ali_al-3ajamy/051.mp3","StartMs":202332,"EndMs":208361,"DurationMs":6029},{"I":13,"S":51,"V":37,"Url":"https://download.quranicaudio.com/quran/ahmed_ibn_3ali_al-3ajamy/051.mp3","StartMs":208361,"EndMs":215833,"DurationMs":7472},{"I":14,"S":51,"V":38,"Url":"https://download.quranicaudio.com/quran/ahmed_ibn_3ali_al-3ajamy/051.mp3","StartMs":215833,"EndMs":223757,"DurationMs":7924},{"I":15,"S":51,"V":39,"Url":"https://download.quranicaudio.com/quran/ahmed_ibn_3ali_al-3ajamy/051.mp3","StartMs":223757,"EndMs":229297,"DurationMs":5540},{"I":16,"S":51,"V":40,"Url":"https://download.quranicaudio.com/quran/ahmed_ibn_3ali_al-3ajamy/051.mp3","StartMs":229297,"EndMs":236021,"DurationMs":6724},{"I":17,"S":51,"V":41,"Url":"https://download.quranicaudio.com/quran/ahmed_ibn_3ali_al-3ajamy/051.mp3","StartMs":236021,"EndMs":242146,"DurationMs":6125},{"I":18,"S":51,"V":42,"Url":"https://download.quranicaudio.com/quran/ahmed_ibn_3ali_al-3ajamy/051.mp3","StartMs":242146,"EndMs":248821,"DurationMs":6675},{"I":19,"S":51,"V":43,"Url":"https://download.quranicaudio.com/quran/ahmed_ibn_3ali_al-3ajamy/051.mp3","StartMs":248821,"EndMs":254896,"DurationMs":6075},{"I":20,"S":51,"V":44,"Url":"https://download.quranicaudio.com/quran/ahmed_ibn_3ali_al-3ajamy/051.mp3","StartMs":254896,"EndMs":262172,"DurationMs":7276},{"I":21,"S":51,"V":45,"Url":"https://download.quranicaudio.com/quran/ahmed_ibn_3ali_al-3ajamy/051.mp3","StartMs":262172,"EndMs":269546,"DurationMs":7374},{"I":22,"S":51,"V":46,"Url":"https://download.quranicaudio.com/quran/ahmed_ibn_3ali_al-3ajamy/051.mp3","StartMs":269546,"EndMs":278358,"DurationMs":8812}]}